Workbook

Sheet Scenarios probability
G2: Final ROC Ranking | I2: Probs
G3: P(S1∣S1,S2,S3) | H3: 3 | I3: 0.11111111
G4: P(S2∣S1,S2,S3) | H4: 1 | I4: 0.61111111
G5: P(S3∣S1,S2,S3) | H5: 2 | I5: 0.27777778

Sheet Elicitation of functions
A1: Attribute | B1: Scale type | C1: Worst plausible consequence | D1: Best plausible consequence | E1: Scale description
A2: Achievement of learning outcomes | B2: Natural percentage | C2: 0.65 | D2: 0.95 | E2: % of students meeting competency targets
A3: Completion and progression | B3: Natural percentage | C3: 0.55 | D3: 0.9 | E3: % of students completing within target time or target+1 year
A4: Learner experience and engagement | B4: Anchored categorical | C4: Very poor | D4: Excellent | E4: 1=Very poor; 2=Poor; 3=Acceptable; 4=Good; 5=Excellent
A5: Accessibility flexibility and equity | B5: Count / extent | C5: 0 | D5: 4 | E5: Number of learner profiles well supported: 0=None; 1=One; 2=Two; 3=Three; 4=All four
A6: Integrity of assessment | B6: Anchored categorical | C6: Fragile | D6: Exemplary | E6: 1=Fragile; 2=Basic; 3=Robust; 4=Exemplary
A7: Strategic control / autonomy | B7: Natural percentage | C7: 0.2 | D7: 0.9 | E7: % of critical learning/assessment/data infrastructure under Aalto or trusted regional control | F7: Achievement of learning outcomes
A8: External relevance and employability | B8: Natural percentage | C8: 0.65 | D8: 0.95 | E8: percentage of graduates in relevant employment or further study within 12 months | F8: t- | G8: t+ | H8: t | I8: U(x) | K8: U(x) | L8: t
A9: Global attractiveness / reputation | B9: Anchored categorical | C9: Local | D9: Globally distinctive | E9: 1=Local; 2=National; 3=Nordic-Baltic; 4=European; 5=Globally distinctive | F9: 0.65 | G9: 0.95 | H9: 0.8 | I9: 0.5 | K9: 0.65 | L9: 0
F10: =F9 -> 0.65 | G10: =H9 -> 0.8 | H10: 0.72 | I10: 0.25 | K10: 0.72 | L10: 0.25
F11: =H9 -> 0.8 | G11: =G9 -> 0.95 | H11: 0.85 | I11: 0.75 | K11: 0.8 | L11: 0.5
G12: x_0 | H12: 0.65 | I12: 0 | K12: 0.85 | L12: 0.75
G13: x_1 | H13: 0.95 | I13: 1 | K13: 0.95 | L13: 1
H14: 0.82 | I14: =IF(H14<H10,(I10-I12)/(H10-H12)*(H14-H12)+I12,IF(H14<H9,(I9-I10)/(H9-H10)*(H14-H10)+I10,IF(H14<H11,(I11-I9)/(H11-H9)*(H14-H9)+I9,(I13-I11)/(H13-H11)*(H14-H11)+I11))) -> 0.6
F17: Completion and progression | N17: t | O17: U(x)
F18: t- | G18: t+ | H18: t | I18: U(x) | N18: 0.55 | O18: 0
F19: 0.55 | G19: 0.9 | H19: 0.72 | I19: 0.5 | N19: 0.65 | O19: 0.25
F20: =F19 -> 0.55 | G20: =H19 -> 0.72 | H20: 0.65 | I20: 0.25 | N20: 0.72 | O20: 0.5
F21: =H19 -> 0.72 | G21: =G19 -> 0.9 | H21: 0.8 | I21: 0.75 | N21: 0.8 | O21: 0.75
G22: x_0 | H22: 0.55 | I22: 0 | N22: 0.9 | O22: 1
G23: x_1 | H23: 0.9 | I23: 1
H24: 0.55 | I24: =IF(H24<H20,(I20-I22)/(H20-H22)*(H24-H22)+I22,IF(H24<H19,(I19-I20)/(H19-H20)*(H24-H20)+I20,IF(H24<H21,(I21-I19)/(H21-H19)*(H24-H19)+I19,(I23-I21)/(H23-H21)*(H24-H21)+I21))) -> 0
F27: Learner experience and engagement | K27: U(x)
F28: t | G28: t- | H28: t+ | I28: p of t- | J28: p of t+
F29: Very poor | K29: 0
F30: Poor | G30: Very poor | H30: Excellent | I30: 0.8 | J30: 0.2 | K30: =I30 * $K$29 + J30 * $K$33 -> 0.2
F31: Acceptable | G31: Very poor | H31: Excellent | I31: 0.6 | J31: 0.4 | K31: =I31 * $K$29 + J31 * $K$33 -> 0.4
F32: Good | G32: Very poor | H32: Excellent | I32: 0.3 | J32: 0.7 | K32: =I32 * $K$29 + J32 * $K$33 -> 0.7
F33: Excellent | K33: 1
F37: Accessibility flexibility and equity | K37: U(x)
F38: t | G38: t- | H38: t+ | I38: p of t- | J38: p of t+
F39: 0 | K39: 0
F40: 1 | G40: 0 | H40: 4 | I40: 0.7 | J40: 0.3 | K40: =I40 * $K$29 + J40 * $K$33 -> 0.3
F41: 2 | G41: 0 | H41: 4 | I41: 0.5 | J41: 0.5 | K41: =I41 * $K$29 + J41 * $K$33 -> 0.5
F42: 3 | G42: 0 | H42: 4 | I42: 0.2 | J42: 0.8 | K42: =I42 * $K$29 + J42 * $K$33 -> 0.8
F43: 4 | K43: 1
F47: Integrity of Assessment | K47: U(x)
F48: t | G48: t- | H48: t+ | I48: p of t- | J48: p of t+
F49: Fragile | K49: 0
F50: Basic | G50: Fragile | H50: Exemplary | I50: 0.5 | J50: 0.5 | K50: =I50 * $K$29 + J50 * $K$33 -> 0.5
F51: Robust | G51: Fragile | H51: Exemplary | I51: 0.25 | J51: 0.75 | K51: =I51 * $K$29 + J51 * $K$33 -> 0.75
F52: Exemplary | K52: 1
F57: Strategic control / autonomy
F58: t- | G58: t+ | H58: t | I58: U(x) | K58: t | L58: U(x)
F59: 0.2 | G59: 0.9 | H59: 0.45 | I59: 0.5 | K59: 0.2 | L59: 0
F60: =F59 -> 0.2 | G60: =H59 -> 0.45 | H60: 0.3 | I60: 0.25 | K60: 0.3 | L60: 0.25
F61: =H59 -> 0.45 | G61: =G59 -> 0.9 | H61: 0.75 | I61: 0.75 | K61: 0.45 | L61: 0.5
G62: x_0 | H62: 0.2 | I62: 0 | K62: 0.75 | L62: 0.75
G63: x_1 | H63: 0.9 | I63: 1 | K63: 0.9 | L63: 1
H64: 0.8 | I64: =IF(H64<H60,(I60-I62)/(H60-H62)*(H64-H62)+I62,IF(H64<H59,(I59-I60)/(H59-H60)*(H64-H60)+I60,IF(H64<H61,(I61-I59)/(H61-H59)*(H64-H59)+I59,(I63-I61)/(H63-H61)*(H64-H61)+I61))) -> 0.83333333
F67: External relevance and employability
F68: t- | G68: t+ | H68: t | I68: U(x) | K68: t | L68: U(x)
F69: 0.65 | G69: 0.95 | H69: 0.82 | I69: 0.5 | K69: 0.65 | L69: 0
F70: =F69 -> 0.65 | G70: =H69 -> 0.82 | H70: 0.71 | I70: 0.25 | K70: 0.71 | L70: 0.25
F71: =H69 -> 0.82 | G71: =G69 -> 0.95 | H71: 0.9 | I71: 0.75 | K71: 0.82 | L71: 0.5
G72: x_0 | H72: 0.65 | I72: 0 | K72: 0.9 | L72: 0.75
G73: x_1 | H73: 0.95 | I73: 1 | K73: 0.95 | L73: 1
H74: 0.8 | I74: =IF(H74<H70,(I70-I72)/(H70-H72)*(H74-H72)+I72,IF(H74<H69,(I69-I70)/(H69-H70)*(H74-H70)+I70,IF(H74<H71,(I71-I69)/(H71-H69)*(H74-H69)+I69,(I73-I71)/(H73-H71)*(H74-H71)+I71))) -> 0.45454545
F77: Global Attractiveness | K77: U(x)
F78: t | G78: t- | H78: t+ | I78: p of t- | J78: p of t+
F79: 1 | K79: 0
F80: 2 | G80: 1 | H80: 5 | I80: 0.8 | J80: 0.2 | K80: =I80 * $K$29 + J80 * $K$33 -> 0.2
F81: 3 | G81: 1 | H81: 5 | I81: 0.65 | J81: 0.35 | K81: =I81 * $K$29 + J81 * $K$33 -> 0.35
F82: 4 | G82: 1 | H82: 5 | I82: 0.3 | J82: 0.7 | K82: =I82 * $K$29 + J82 * $K$33 -> 0.7
F83: 5 | K83: 1

Sheet Elicitation of weights
A1: Attribute swung from worst to best | B1: Consequence to compare | C1: Rank | D1: Wj | E1: wj (ROC)
A2: (Benchmark) | B2: 65%,55%,1,0,1,20%,65%,1 | G2: =1/8 -> 0.125
A3: Achievement of learning outcomes | B3: 95%,55%,1,0,1,20%,65%,1 | C3: 5 | D3: =C3^(-1) -> 0.2 | E3: =(SUMIF($C$3:$C$10,">="&C3,$D$3:$D$10))*$G$2 -> 0.079315476
A4: Completion and progression | B4: 65%,90%,1,0,1,20%,65%,1 | C4: 2 | D4: =C4^(-1) -> 0.5 | E4: =(SUMIF($C$3:$C$10,">="&C4,$D$3:$D$10))*$G$2 -> 0.21473214
A5: Learner experience and engagement | B5: 65%,55%,5,0,1,20%,65%,1 | C5: 4 | D5: =C5^(-1) -> 0.25 | E5: =(SUMIF($C$3:$C$10,">="&C5,$D$3:$D$10))*$G$2 -> 0.11056548
A6: Accessibility flexibility and equity | B6: 65%,55%,1,4,1,20%,65%,1 | C6: 7 | D6: =C6^(-1) -> 0.14285714 | E6: =(SUMIF($C$3:$C$10,">="&C6,$D$3:$D$10))*$G$2 -> 0.033482143
A7: Integrity of assessment | B7: 65%,55%,1,0,4,20%,65%,1 | C7: 8 | D7: =C7^(-1) -> 0.125 | E7: =(SUMIF($C$3:$C$10,">="&C7,$D$3:$D$10))*$G$2 -> 0.015625
A8: Strategic control / autonomy | B8: 65%,55%,1,0,1,90%,65%,1 | C8: 6 | D8: =C8^(-1) -> 0.16666667 | E8: =(SUMIF($C$3:$C$10,">="&C8,$D$3:$D$10))*$G$2 -> 0.054315476
A9: External relevance and employability | B9: 65%,55%,1,0,1,20%,95%,1 | C9: 1 | D9: =C9^(-1) -> 1 | E9: =(SUMIF($C$3:$C$10,">="&C9,$D$3:$D$10))*$G$2 -> 0.33973214
A10: Global attractiveness / reputation | B10: 65%,55%,1,0,1,20%,65%,5 | C10: 3 | D10: =C10^(-1) -> 0.33333333 | E10: =(SUMIF($C$3:$C$10,">="&C10,$D$3:$D$10))*$G$2 -> 0.15223214
C11: Total | D11: 0 | E11: =SUM(E3:E10) -> 1

Sheet Action Performance by Scenario
L2: Attribute-specific value scores (0-1) linked from elicited value functions
B4: Scenario 1: Competitive Global Campus​ | L4: Scenario 1: Competitive Global Campus - Attribute-specific value scores
B5: Action | C5: Achievement of learning outcomes (65-95%) | D5: Completion and progression (55-90%) | E5: Learner experience and engagement | F5: Accessibility, flexibility and equity (0-4) | G5: Integrity of assessment | H5: Strategic control / autonomy (20-90%) | I5: External relevance and employability (65-95%) | J5: Global attractiveness / reputation (1-5) | L5: Action | M5: Achievement of learning outcomes (65-95%) | N5: Completion and progression (55-90%) | O5: Learner experience and engagement | P5: Accessibility, flexibility and equity (0-4) | Q5: Integrity of assessment | R5: Strategic control / autonomy (20-90%) | S5: External relevance and employability (65-95%) | T5: Global attractiveness / reputation (1-5)
B6: AI-Enabled Student Guidance | C6: 0.82 | D6: 0.78 | E6: Good | F6: 3 | G6: Basic | H6: 0.4 | I6: 0.82 | J6: 3 | L6: =B6 -> AI-Enabled Student Guidance | M6: =IF(C6<'Elicitation of functions'!$H$10,('Elicitation of functions'!$I$10-'Elicitation of functions'!$I$12)/('Elicitation of functions'!$H$10-'Elicitation of functions'!$H$12)*(C6-'Elicitation of functions'!$H$12)+'Elicitation of functions'!$I$12,IF(C6<'Elicitation of functions'!$H$9,('Elicitation of functions'!$I$9-'Elicitation of functions'!$I$10)/('Elicitation of functions'!$H$9-'Elicitation of functions'!$H$10)*(C6-'Elicitation of functions'!$H$10)+'Elicitation of functions'!$I$10,IF(C6<'Elicitation of functions'!$H$11,('Elicitation of functions'!$I$11-'Elicitation of functions'!$I$9)/('Elicitation of functions'!$H$11-'Elicitation of functions'!$H$9)*(C6-'Elicitation of functions'!$H$9)+'Elicitation of functions'!$I$9,('Elicitation of functions'!$I$13-'Elicitation of functions'!$I$11)/('Elicitation of functions'!$H$13-'Elicitation of functions'!$H$11)*(C6-'Elicitation of functions'!$H$11)+'Elicitation of functions'!$I$11))) -> 0.6 | N6: =IF(D6<'Elicitation of functions'!$H$20,('Elicitation of functions'!$I$20-'Elicitation of functions'!$I$22)/('Elicitation of functions'!$H$20-'Elicitation of functions'!$H$22)*(D6-'Elicitation of functions'!$H$22)+'Elicitation of functions'!$I$22,IF(D6<'Elicitation of functions'!$H$19,('Elicitation of functions'!$I$19-'Elicitation of functions'!$I$20)/('Elicitation of functions'!$H$19-'Elicitation of functions'!$H$20)*(D6-'Elicitation of functions'!$H$20)+'Elicitation of functions'!$I$20,IF(D6<'Elicitation of functions'!$H$21,('Elicitation of functions'!$I$21-'Elicitation of functions'!$I$19)/('Elicitation of functions'!$H$21-'Elicitation of functions'!$H$19)*(D6-'Elicitation of functions'!$H$19)+'Elicitation of functions'!$I$19,('Elicitation of functions'!$I$23-'Elicitation of functions'!$I$21)/('Elicitation of functions'!$H$23-'Elicitation of functions'!$H$21)*(D6-'Elicitation of functions'!$H$21)+'Elicitation of functions'!$I$21))) -> 0.6875 | O6: =INDEX('Elicitation of functions'!$K$29:$K$33,MATCH(E6,'Elicitation of functions'!$F$29:$F$33,0)) -> 0.7 | P6: =INDEX('Elicitation of functions'!$K$39:$K$43,MATCH(F6,'Elicitation of functions'!$F$39:$F$43,0)) -> 0.8 | Q6: =INDEX('Elicitation of functions'!$K$49:$K$52,MATCH(G6,'Elicitation of functions'!$F$49:$F$52,0)) -> 0.5 | R6: =IF(H6<'Elicitation of functions'!$H$60,('Elicitation of functions'!$I$60-'Elicitation of functions'!$I$62)/('Elicitation of functions'!$H$60-'Elicitation of functions'!$H$62)*(H6-'Elicitation of functions'!$H$62)+'Elicitation of functions'!$I$62,IF(H6<'Elicitation of functions'!$H$59,('Elicitation of functions'!$I$59-'Elicitation of functions'!$I$60)/('Elicitation of functions'!$H$59-'Elicitation of functions'!$H$60)*(H6-'Elicitation of functions'!$H$60)+'Elicitation of functions'!$I$60,IF(H6<'Elicitation of functions'!$H$61,('Elicitation of functions'!$I$61-'Elicitation of functions'!$I$59)/('Elicitation of functions'!$H$61-'Elicitation of functions'!$H$59)*(H6-'Elicitation of functions'!$H$59)+'Elicitation of functions'!$I$59,('Elicitation of functions'!$I$63-'Elicitation of functions'!$I$61)/('Elicitation of functions'!$H$63-'Elicitation of functions'!$H$61)*(H6-'Elicitation of functions'!$H$61)+'Elicitation of functions'!$I$61))) -> 0.41666667 | S6: =IF(I6<'Elicitation of functions'!$H$70,('Elicitation of functions'!$I$70-'Elicitation of functions'!$I$72)/('Elicitation of functions'!$H$70-'Elicitation of functions'!$H$72)*(I6-'Elicitation of functions'!$H$72)+'Elicitation of functions'!$I$72,IF(I6<'Elicitation of functions'!$H$69,('Elicitation of functions'!$I$69-'Elicitation of functions'!$I$70)/('Elicitation of functions'!$H$69-'Elicitation of functions'!$H$70)*(I6-'Elicitation of functions'!$H$70)+'Elicitation of functions'!$I$70,IF(I6<'Elicitation of functions'!$H$71,('Elicitation of functions'!$I$71-'Elicitation of functions'!$I$69)/('Elicitation of functions'!$H$71-'Elicitation of functions'!$H$69)*(I6-'Elicitation of functions'!$H$69)+'Elicitation of functions'!$I$69,('Elicitation of functions'!$I$73-'Elicitation of functions'!$I$71)/('Elicitation of functions'!$H$73-'Elicitation of functions'!$H$71)*(I6-'Elicitation of functions'!$H$71)+'Elicitation of functions'!$I$71))) -> 0.5 | T6: =INDEX('Elicitation of functions'!$K$79:$K$83,MATCH(J6,'Elicitation of functions'!$F$79:$F$83,0)) -> 0.35 | V6: 0.8 | W6: 0.5 | X6: 0.416667 | Y6: 0.5 | Z6: 0.35
B7: Elite Mentor Network / Smart Work-Study | C7: 0.85 | D7: 0.75 | E7: Excellent | F7: 1 | G7: Robust | H7: 0.45 | I7: 0.9 | J7: 4 | L7: =B7 -> Elite Mentor Network / Smart Work-Study | M7: =IF(C7<'Elicitation of functions'!$H$10,('Elicitation of functions'!$I$10-'Elicitation of functions'!$I$12)/('Elicitation of functions'!$H$10-'Elicitation of functions'!$H$12)*(C7-'Elicitation of functions'!$H$12)+'Elicitation of functions'!$I$12,IF(C7<'Elicitation of functions'!$H$9,('Elicitation of functions'!$I$9-'Elicitation of functions'!$I$10)/('Elicitation of functions'!$H$9-'Elicitation of functions'!$H$10)*(C7-'Elicitation of functions'!$H$10)+'Elicitation of functions'!$I$10,IF(C7<'Elicitation of functions'!$H$11,('Elicitation of functions'!$I$11-'Elicitation of functions'!$I$9)/('Elicitation of functions'!$H$11-'Elicitation of functions'!$H$9)*(C7-'Elicitation of functions'!$H$9)+'Elicitation of functions'!$I$9,('Elicitation of functions'!$I$13-'Elicitation of functions'!$I$11)/('Elicitation of functions'!$H$13-'Elicitation of functions'!$H$11)*(C7-'Elicitation of functions'!$H$11)+'Elicitation of functions'!$I$11))) -> 0.75 | N7: =IF(D7<'Elicitation of functions'!$H$20,('Elicitation of functions'!$I$20-'Elicitation of functions'!$I$22)/('Elicitation of functions'!$H$20-'Elicitation of functions'!$H$22)*(D7-'Elicitation of functions'!$H$22)+'Elicitation of functions'!$I$22,IF(D7<'Elicitation of functions'!$H$19,('Elicitation of functions'!$I$19-'Elicitation of functions'!$I$20)/('Elicitation of functions'!$H$19-'Elicitation of functions'!$H$20)*(D7-'Elicitation of functions'!$H$20)+'Elicitation of functions'!$I$20,IF(D7<'Elicitation of functions'!$H$21,('Elicitation of functions'!$I$21-'Elicitation of functions'!$I$19)/('Elicitation of functions'!$H$21-'Elicitation of functions'!$H$19)*(D7-'Elicitation of functions'!$H$19)+'Elicitation of functions'!$I$19,('Elicitation of functions'!$I$23-'Elicitation of functions'!$I$21)/('Elicitation of functions'!$H$23-'Elicitation of functions'!$H$21)*(D7-'Elicitation of functions'!$H$21)+'Elicitation of functions'!$I$21))) -> 0.59375 | O7: =INDEX('Elicitation of functions'!$K$29:$K$33,MATCH(E7,'Elicitation of functions'!$F$29:$F$33,0)) -> 1 | P7: =INDEX('Elicitation of functions'!$K$39:$K$43,MATCH(F7,'Elicitation of functions'!$F$39:$F$43,0)) -> 0.3 | Q7: =INDEX('Elicitation of functions'!$K$49:$K$52,MATCH(G7,'Elicitation of functions'!$F$49:$F$52,0)) -> 0.75 | R7: =IF(H7<'Elicitation of functions'!$H$60,('Elicitation of functions'!$I$60-'Elicitation of functions'!$I$62)/('Elicitation of functions'!$H$60-'Elicitation of functions'!$H$62)*(H7-'Elicitation of functions'!$H$62)+'Elicitation of functions'!$I$62,IF(H7<'Elicitation of functions'!$H$59,('Elicitation of functions'!$I$59-'Elicitation of functions'!$I$60)/('Elicitation of functions'!$H$59-'Elicitation of functions'!$H$60)*(H7-'Elicitation of functions'!$H$60)+'Elicitation of functions'!$I$60,IF(H7<'Elicitation of functions'!$H$61,('Elicitation of functions'!$I$61-'Elicitation of functions'!$I$59)/('Elicitation of functions'!$H$61-'Elicitation of functions'!$H$59)*(H7-'Elicitation of functions'!$H$59)+'Elicitation of functions'!$I$59,('Elicitation of functions'!$I$63-'Elicitation of functions'!$I$61)/('Elicitation of functions'!$H$63-'Elicitation of functions'!$H$61)*(H7-'Elicitation of functions'!$H$61)+'Elicitation of functions'!$I$61))) -> 0.5 | S7: =IF(I7<'Elicitation of functions'!$H$70,('Elicitation of functions'!$I$70-'Elicitation of functions'!$I$72)/('Elicitation of functions'!$H$70-'Elicitation of functions'!$H$72)*(I7-'Elicitation of functions'!$H$72)+'Elicitation of functions'!$I$72,IF(I7<'Elicitation of functions'!$H$69,('Elicitation of functions'!$I$69-'Elicitation of functions'!$I$70)/('Elicitation of functions'!$H$69-'Elicitation of functions'!$H$70)*(I7-'Elicitation of functions'!$H$70)+'Elicitation of functions'!$I$70,IF(I7<'Elicitation of functions'!$H$71,('Elicitation of functions'!$I$71-'Elicitation of functions'!$I$69)/('Elicitation of functions'!$H$71-'Elicitation of functions'!$H$69)*(I7-'Elicitation of functions'!$H$69)+'Elicitation of functions'!$I$69,('Elicitation of functions'!$I$73-'Elicitation of functions'!$I$71)/('Elicitation of functions'!$H$73-'Elicitation of functions'!$H$71)*(I7-'Elicitation of functions'!$H$71)+'Elicitation of functions'!$I$71))) -> 0.75 | T7: =INDEX('Elicitation of functions'!$K$79:$K$83,MATCH(J7,'Elicitation of functions'!$F$79:$F$83,0)) -> 0.7 | V7: 0.3 | W7: 0.75 | X7: 0.5 | Y7: 0.75 | Z7: 0.7
B8: AI Governance Board / Assessment Integrity | C8: 0.75 | D8: 0.65 | E8: Poor | F8: 2 | G8: Exemplary | H8: 0.6 | I8: 0.8 | J8: 3 | L8: =B8 -> AI Governance Board / Assessment Integrity | M8: =IF(C8<'Elicitation of functions'!$H$10,('Elicitation of functions'!$I$10-'Elicitation of functions'!$I$12)/('Elicitation of functions'!$H$10-'Elicitation of functions'!$H$12)*(C8-'Elicitation of functions'!$H$12)+'Elicitation of functions'!$I$12,IF(C8<'Elicitation of functions'!$H$9,('Elicitation of functions'!$I$9-'Elicitation of functions'!$I$10)/('Elicitation of functions'!$H$9-'Elicitation of functions'!$H$10)*(C8-'Elicitation of functions'!$H$10)+'Elicitation of functions'!$I$10,IF(C8<'Elicitation of functions'!$H$11,('Elicitation of functions'!$I$11-'Elicitation of functions'!$I$9)/('Elicitation of functions'!$H$11-'Elicitation of functions'!$H$9)*(C8-'Elicitation of functions'!$H$9)+'Elicitation of functions'!$I$9,('Elicitation of functions'!$I$13-'Elicitation of functions'!$I$11)/('Elicitation of functions'!$H$13-'Elicitation of functions'!$H$11)*(C8-'Elicitation of functions'!$H$11)+'Elicitation of functions'!$I$11))) -> 0.34375 | N8: =IF(D8<'Elicitation of functions'!$H$20,('Elicitation of functions'!$I$20-'Elicitation of functions'!$I$22)/('Elicitation of functions'!$H$20-'Elicitation of functions'!$H$22)*(D8-'Elicitation of functions'!$H$22)+'Elicitation of functions'!$I$22,IF(D8<'Elicitation of functions'!$H$19,('Elicitation of functions'!$I$19-'Elicitation of functions'!$I$20)/('Elicitation of functions'!$H$19-'Elicitation of functions'!$H$20)*(D8-'Elicitation of functions'!$H$20)+'Elicitation of functions'!$I$20,IF(D8<'Elicitation of functions'!$H$21,('Elicitation of functions'!$I$21-'Elicitation of functions'!$I$19)/('Elicitation of functions'!$H$21-'Elicitation of functions'!$H$19)*(D8-'Elicitation of functions'!$H$19)+'Elicitation of functions'!$I$19,('Elicitation of functions'!$I$23-'Elicitation of functions'!$I$21)/('Elicitation of functions'!$H$23-'Elicitation of functions'!$H$21)*(D8-'Elicitation of functions'!$H$21)+'Elicitation of functions'!$I$21))) -> 0.25 | O8: =INDEX('Elicitation of functions'!$K$29:$K$33,MATCH(E8,'Elicitation of functions'!$F$29:$F$33,0)) -> 0.2 | P8: =INDEX('Elicitation of functions'!$K$39:$K$43,MATCH(F8,'Elicitation of functions'!$F$39:$F$43,0)) -> 0.5 | Q8: =INDEX('Elicitation of functions'!$K$49:$K$52,MATCH(G8,'Elicitation of functions'!$F$49:$F$52,0)) -> 1 | R8: =IF(H8<'Elicitation of functions'!$H$60,('Elicitation of functions'!$I$60-'Elicitation of functions'!$I$62)/('Elicitation of functions'!$H$60-'Elicitation of functions'!$H$62)*(H8-'Elicitation of functions'!$H$62)+'Elicitation of functions'!$I$62,IF(H8<'Elicitation of functions'!$H$59,('Elicitation of functions'!$I$59-'Elicitation of functions'!$I$60)/('Elicitation of functions'!$H$59-'Elicitation of functions'!$H$60)*(H8-'Elicitation of functions'!$H$60)+'Elicitation of functions'!$I$60,IF(H8<'Elicitation of functions'!$H$61,('Elicitation of functions'!$I$61-'Elicitation of functions'!$I$59)/('Elicitation of functions'!$H$61-'Elicitation of functions'!$H$59)*(H8-'Elicitation of functions'!$H$59)+'Elicitation of functions'!$I$59,('Elicitation of functions'!$I$63-'Elicitation of functions'!$I$61)/('Elicitation of functions'!$H$63-'Elicitation of functions'!$H$61)*(H8-'Elicitation of functions'!$H$61)+'Elicitation of functions'!$I$61))) -> 0.625 | S8: =IF(I8<'Elicitation of functions'!$H$70,('Elicitation of functions'!$I$70-'Elicitation of functions'!$I$72)/('Elicitation of functions'!$H$70-'Elicitation of functions'!$H$72)*(I8-'Elicitation of functions'!$H$72)+'Elicitation of functions'!$I$72,IF(I8<'Elicitation of functions'!$H$69,('Elicitation of functions'!$I$69-'Elicitation of functions'!$I$70)/('Elicitation of functions'!$H$69-'Elicitation of functions'!$H$70)*(I8-'Elicitation of functions'!$H$70)+'Elicitation of functions'!$I$70,IF(I8<'Elicitation of functions'!$H$71,('Elicitation of functions'!$I$71-'Elicitation of functions'!$I$69)/('Elicitation of functions'!$H$71-'Elicitation of functions'!$H$69)*(I8-'Elicitation of functions'!$H$69)+'Elicitation of functions'!$I$69,('Elicitation of functions'!$I$73-'Elicitation of functions'!$I$71)/('Elicitation of functions'!$H$73-'Elicitation of functions'!$H$71)*(I8-'Elicitation of functions'!$H$71)+'Elicitation of functions'!$I$71))) -> 0.45454545 | T8: =INDEX('Elicitation of functions'!$K$79:$K$83,MATCH(J8,'Elicitation of functions'!$F$79:$F$83,0)) -> 0.35 | V8: 0.5 | W8: 1 | X8: 0.625 | Y8: 0.454545 | Z8: 0.35
B9: Aalto-Controlled Core Infrastructure | C9: 0.8 | D9: 0.72 | E9: Acceptable | F9: 2 | G9: Robust | H9: 0.8 | I9: 0.82 | J9: 2 | L9: =B9 -> Aalto-Controlled Core Infrastructure | M9: =IF(C9<'Elicitation of functions'!$H$10,('Elicitation of functions'!$I$10-'Elicitation of functions'!$I$12)/('Elicitation of functions'!$H$10-'Elicitation of functions'!$H$12)*(C9-'Elicitation of functions'!$H$12)+'Elicitation of functions'!$I$12,IF(C9<'Elicitation of functions'!$H$9,('Elicitation of functions'!$I$9-'Elicitation of functions'!$I$10)/('Elicitation of functions'!$H$9-'Elicitation of functions'!$H$10)*(C9-'Elicitation of functions'!$H$10)+'Elicitation of functions'!$I$10,IF(C9<'Elicitation of functions'!$H$11,('Elicitation of functions'!$I$11-'Elicitation of functions'!$I$9)/('Elicitation of functions'!$H$11-'Elicitation of functions'!$H$9)*(C9-'Elicitation of functions'!$H$9)+'Elicitation of functions'!$I$9,('Elicitation of functions'!$I$13-'Elicitation of functions'!$I$11)/('Elicitation of functions'!$H$13-'Elicitation of functions'!$H$11)*(C9-'Elicitation of functions'!$H$11)+'Elicitation of functions'!$I$11))) -> 0.5 | N9: =IF(D9<'Elicitation of functions'!$H$20,('Elicitation of functions'!$I$20-'Elicitation of functions'!$I$22)/('Elicitation of functions'!$H$20-'Elicitation of functions'!$H$22)*(D9-'Elicitation of functions'!$H$22)+'Elicitation of functions'!$I$22,IF(D9<'Elicitation of functions'!$H$19,('Elicitation of functions'!$I$19-'Elicitation of functions'!$I$20)/('Elicitation of functions'!$H$19-'Elicitation of functions'!$H$20)*(D9-'Elicitation of functions'!$H$20)+'Elicitation of functions'!$I$20,IF(D9<'Elicitation of functions'!$H$21,('Elicitation of functions'!$I$21-'Elicitation of functions'!$I$19)/('Elicitation of functions'!$H$21-'Elicitation of functions'!$H$19)*(D9-'Elicitation of functions'!$H$19)+'Elicitation of functions'!$I$19,('Elicitation of functions'!$I$23-'Elicitation of functions'!$I$21)/('Elicitation of functions'!$H$23-'Elicitation of functions'!$H$21)*(D9-'Elicitation of functions'!$H$21)+'Elicitation of functions'!$I$21))) -> 0.5 | O9: =INDEX('Elicitation of functions'!$K$29:$K$33,MATCH(E9,'Elicitation of functions'!$F$29:$F$33,0)) -> 0.4 | P9: =INDEX('Elicitation of functions'!$K$39:$K$43,MATCH(F9,'Elicitation of functions'!$F$39:$F$43,0)) -> 0.5 | Q9: =INDEX('Elicitation of functions'!$K$49:$K$52,MATCH(G9,'Elicitation of functions'!$F$49:$F$52,0)) -> 0.75 | R9: =IF(H9<'Elicitation of functions'!$H$60,('Elicitation of functions'!$I$60-'Elicitation of functions'!$I$62)/('Elicitation of functions'!$H$60-'Elicitation of functions'!$H$62)*(H9-'Elicitation of functions'!$H$62)+'Elicitation of functions'!$I$62,IF(H9<'Elicitation of functions'!$H$59,('Elicitation of functions'!$I$59-'Elicitation of functions'!$I$60)/('Elicitation of functions'!$H$59-'Elicitation of functions'!$H$60)*(H9-'Elicitation of functions'!$H$60)+'Elicitation of functions'!$I$60,IF(H9<'Elicitation of functions'!$H$61,('Elicitation of functions'!$I$61-'Elicitation of functions'!$I$59)/('Elicitation of functions'!$H$61-'Elicitation of functions'!$H$59)*(H9-'Elicitation of functions'!$H$59)+'Elicitation of functions'!$I$59,('Elicitation of functions'!$I$63-'Elicitation of functions'!$I$61)/('Elicitation of functions'!$H$63-'Elicitation of functions'!$H$61)*(H9-'Elicitation of functions'!$H$61)+'Elicitation of functions'!$I$61))) -> 0.83333333 | S9: =IF(I9<'Elicitation of functions'!$H$70,('Elicitation of functions'!$I$70-'Elicitation of functions'!$I$72)/('Elicitation of functions'!$H$70-'Elicitation of functions'!$H$72)*(I9-'Elicitation of functions'!$H$72)+'Elicitation of functions'!$I$72,IF(I9<'Elicitation of functions'!$H$69,('Elicitation of functions'!$I$69-'Elicitation of functions'!$I$70)/('Elicitation of functions'!$H$69-'Elicitation of functions'!$H$70)*(I9-'Elicitation of functions'!$H$70)+'Elicitation of functions'!$I$70,IF(I9<'Elicitation of functions'!$H$71,('Elicitation of functions'!$I$71-'Elicitation of functions'!$I$69)/('Elicitation of functions'!$H$71-'Elicitation of functions'!$H$69)*(I9-'Elicitation of functions'!$H$69)+'Elicitation of functions'!$I$69,('Elicitation of functions'!$I$73-'Elicitation of functions'!$I$71)/('Elicitation of functions'!$H$73-'Elicitation of functions'!$H$71)*(I9-'Elicitation of functions'!$H$71)+'Elicitation of functions'!$I$71))) -> 0.5 | T9: =INDEX('Elicitation of functions'!$K$79:$K$83,MATCH(J9,'Elicitation of functions'!$F$79:$F$83,0)) -> 0.2 | V9: 0.5 | W9: 0.75 | X9: 0.833333 | Y9: 0.5 | Z9: 0.2
B10: Aalto-Certified Micro-Credentials | C10: 0.8 | D10: 0.75 | E10: Good | F10: 4 | G10: Basic | H10: 0.5 | I10: 0.88 | J10: 4 | L10: =B10 -> Aalto-Certified Micro-Credentials | M10: =IF(C10<'Elicitation of functions'!$H$10,('Elicitation of functions'!$I$10-'Elicitation of functions'!$I$12)/('Elicitation of functions'!$H$10-'Elicitation of functions'!$H$12)*(C10-'Elicitation of functions'!$H$12)+'Elicitation of functions'!$I$12,IF(C10<'Elicitation of functions'!$H$9,('Elicitation of functions'!$I$9-'Elicitation of functions'!$I$10)/('Elicitation of functions'!$H$9-'Elicitation of functions'!$H$10)*(C10-'Elicitation of functions'!$H$10)+'Elicitation of functions'!$I$10,IF(C10<'Elicitation of functions'!$H$11,('Elicitation of functions'!$I$11-'Elicitation of functions'!$I$9)/('Elicitation of functions'!$H$11-'Elicitation of functions'!$H$9)*(C10-'Elicitation of functions'!$H$9)+'Elicitation of functions'!$I$9,('Elicitation of functions'!$I$13-'Elicitation of functions'!$I$11)/('Elicitation of functions'!$H$13-'Elicitation of functions'!$H$11)*(C10-'Elicitation of functions'!$H$11)+'Elicitation of functions'!$I$11))) -> 0.5 | N10: =IF(D10<'Elicitation of functions'!$H$20,('Elicitation of functions'!$I$20-'Elicitation of functions'!$I$22)/('Elicitation of functions'!$H$20-'Elicitation of functions'!$H$22)*(D10-'Elicitation of functions'!$H$22)+'Elicitation of functions'!$I$22,IF(D10<'Elicitation of functions'!$H$19,('Elicitation of functions'!$I$19-'Elicitation of functions'!$I$20)/('Elicitation of functions'!$H$19-'Elicitation of functions'!$H$20)*(D10-'Elicitation of functions'!$H$20)+'Elicitation of functions'!$I$20,IF(D10<'Elicitation of functions'!$H$21,('Elicitation of functions'!$I$21-'Elicitation of functions'!$I$19)/('Elicitation of functions'!$H$21-'Elicitation of functions'!$H$19)*(D10-'Elicitation of functions'!$H$19)+'Elicitation of functions'!$I$19,('Elicitation of functions'!$I$23-'Elicitation of functions'!$I$21)/('Elicitation of functions'!$H$23-'Elicitation of functions'!$H$21)*(D10-'Elicitation of functions'!$H$21)+'Elicitation of functions'!$I$21))) -> 0.59375 | O10: =INDEX('Elicitation of functions'!$K$29:$K$33,MATCH(E10,'Elicitation of functions'!$F$29:$F$33,0)) -> 0.7 | P10: =INDEX('Elicitation of functions'!$K$39:$K$43,MATCH(F10,'Elicitation of functions'!$F$39:$F$43,0)) -> 1 | Q10: =INDEX('Elicitation of functions'!$K$49:$K$52,MATCH(G10,'Elicitation of functions'!$F$49:$F$52,0)) -> 0.5 | R10: =IF(H10<'Elicitation of functions'!$H$60,('Elicitation of functions'!$I$60-'Elicitation of functions'!$I$62)/('Elicitation of functions'!$H$60-'Elicitation of functions'!$H$62)*(H10-'Elicitation of functions'!$H$62)+'Elicitation of functions'!$I$62,IF(H10<'Elicitation of functions'!$H$59,('Elicitation of functions'!$I$59-'Elicitation of functions'!$I$60)/('Elicitation of functions'!$H$59-'Elicitation of functions'!$H$60)*(H10-'Elicitation of functions'!$H$60)+'Elicitation of functions'!$I$60,IF(H10<'Elicitation of functions'!$H$61,('Elicitation of functions'!$I$61-'Elicitation of functions'!$I$59)/('Elicitation of functions'!$H$61-'Elicitation of functions'!$H$59)*(H10-'Elicitation of functions'!$H$59)+'Elicitation of functions'!$I$59,('Elicitation of functions'!$I$63-'Elicitation of functions'!$I$61)/('Elicitation of functions'!$H$63-'Elicitation of functions'!$H$61)*(H10-'Elicitation of functions'!$H$61)+'Elicitation of functions'!$I$61))) -> 0.54166667 | S10: =IF(I10<'Elicitation of functions'!$H$70,('Elicitation of functions'!$I$70-'Elicitation of functions'!$I$72)/('Elicitation of functions'!$H$70-'Elicitation of functions'!$H$72)*(I10-'Elicitation of functions'!$H$72)+'Elicitation of functions'!$I$72,IF(I10<'Elicitation of functions'!$H$69,('Elicitation of functions'!$I$69-'Elicitation of functions'!$I$70)/('Elicitation of functions'!$H$69-'Elicitation of functions'!$H$70)*(I10-'Elicitation of functions'!$H$70)+'Elicitation of functions'!$I$70,IF(I10<'Elicitation of functions'!$H$71,('Elicitation of functions'!$I$71-'Elicitation of functions'!$I$69)/('Elicitation of functions'!$H$71-'Elicitation of functions'!$H$69)*(I10-'Elicitation of functions'!$H$69)+'Elicitation of functions'!$I$69,('Elicitation of functions'!$I$73-'Elicitation of functions'!$I$71)/('Elicitation of functions'!$H$73-'Elicitation of functions'!$H$71)*(I10-'Elicitation of functions'!$H$71)+'Elicitation of functions'!$I$71))) -> 0.6875 | T10: =INDEX('Elicitation of functions'!$K$79:$K$83,MATCH(J10,'Elicitation of functions'!$F$79:$F$83,0)) -> 0.7 | V10: 1 | W10: 0.5 | X10: 0.541667 | Y10: 0.6875 | Z10: 0.7
B11: Pedagogical Training for Staff | C11: 0.85 | D11: 0.78 | E11: Good | F11: 2 | G11: Robust | H11: 0.5 | I11: 0.84 | J11: 3 | L11: =B11 -> Pedagogical Training for Staff | M11: =IF(C11<'Elicitation of functions'!$H$10,('Elicitation of functions'!$I$10-'Elicitation of functions'!$I$12)/('Elicitation of functions'!$H$10-'Elicitation of functions'!$H$12)*(C11-'Elicitation of functions'!$H$12)+'Elicitation of functions'!$I$12,IF(C11<'Elicitation of functions'!$H$9,('Elicitation of functions'!$I$9-'Elicitation of functions'!$I$10)/('Elicitation of functions'!$H$9-'Elicitation of functions'!$H$10)*(C11-'Elicitation of functions'!$H$10)+'Elicitation of functions'!$I$10,IF(C11<'Elicitation of functions'!$H$11,('Elicitation of functions'!$I$11-'Elicitation of functions'!$I$9)/('Elicitation of functions'!$H$11-'Elicitation of functions'!$H$9)*(C11-'Elicitation of functions'!$H$9)+'Elicitation of functions'!$I$9,('Elicitation of functions'!$I$13-'Elicitation of functions'!$I$11)/('Elicitation of functions'!$H$13-'Elicitation of functions'!$H$11)*(C11-'Elicitation of functions'!$H$11)+'Elicitation of functions'!$I$11))) -> 0.75 | N11: =IF(D11<'Elicitation of functions'!$H$20,('Elicitation of functions'!$I$20-'Elicitation of functions'!$I$22)/('Elicitation of functions'!$H$20-'Elicitation of functions'!$H$22)*(D11-'Elicitation of functions'!$H$22)+'Elicitation of functions'!$I$22,IF(D11<'Elicitation of functions'!$H$19,('Elicitation of functions'!$I$19-'Elicitation of functions'!$I$20)/('Elicitation of functions'!$H$19-'Elicitation of functions'!$H$20)*(D11-'Elicitation of functions'!$H$20)+'Elicitation of functions'!$I$20,IF(D11<'Elicitation of functions'!$H$21,('Elicitation of functions'!$I$21-'Elicitation of functions'!$I$19)/('Elicitation of functions'!$H$21-'Elicitation of functions'!$H$19)*(D11-'Elicitation of functions'!$H$19)+'Elicitation of functions'!$I$19,('Elicitation of functions'!$I$23-'Elicitation of functions'!$I$21)/('Elicitation of functions'!$H$23-'Elicitation of functions'!$H$21)*(D11-'Elicitation of functions'!$H$21)+'Elicitation of functions'!$I$21))) -> 0.6875 | O11: =INDEX('Elicitation of functions'!$K$29:$K$33,MATCH(E11,'Elicitation of functions'!$F$29:$F$33,0)) -> 0.7 | P11: =INDEX('Elicitation of functions'!$K$39:$K$43,MATCH(F11,'Elicitation of functions'!$F$39:$F$43,0)) -> 0.5 | Q11: =INDEX('Elicitation of functions'!$K$49:$K$52,MATCH(G11,'Elicitation of functions'!$F$49:$F$52,0)) -> 0.75 | R11: =IF(H11<'Elicitation of functions'!$H$60,('Elicitation of functions'!$I$60-'Elicitation of functions'!$I$62)/('Elicitation of functions'!$H$60-'Elicitation of functions'!$H$62)*(H11-'Elicitation of functions'!$H$62)+'Elicitation of functions'!$I$62,IF(H11<'Elicitation of functions'!$H$59,('Elicitation of functions'!$I$59-'Elicitation of functions'!$I$60)/('Elicitation of functions'!$H$59-'Elicitation of functions'!$H$60)*(H11-'Elicitation of functions'!$H$60)+'Elicitation of functions'!$I$60,IF(H11<'Elicitation of functions'!$H$61,('Elicitation of functions'!$I$61-'Elicitation of functions'!$I$59)/('Elicitation of functions'!$H$61-'Elicitation of functions'!$H$59)*(H11-'Elicitation of functions'!$H$59)+'Elicitation of functions'!$I$59,('Elicitation of functions'!$I$63-'Elicitation of functions'!$I$61)/('Elicitation of functions'!$H$63-'Elicitation of functions'!$H$61)*(H11-'Elicitation of functions'!$H$61)+'Elicitation of functions'!$I$61))) -> 0.54166667 | S11: =IF(I11<'Elicitation of functions'!$H$70,('Elicitation of functions'!$I$70-'Elicitation of functions'!$I$72)/('Elicitation of functions'!$H$70-'Elicitation of functions'!$H$72)*(I11-'Elicitation of functions'!$H$72)+'Elicitation of functions'!$I$72,IF(I11<'Elicitation of functions'!$H$69,('Elicitation of functions'!$I$69-'Elicitation of functions'!$I$70)/('Elicitation of functions'!$H$69-'Elicitation of functions'!$H$70)*(I11-'Elicitation of functions'!$H$70)+'Elicitation of functions'!$I$70,IF(I11<'Elicitation of functions'!$H$71,('Elicitation of functions'!$I$71-'Elicitation of functions'!$I$69)/('Elicitation of functions'!$H$71-'Elicitation of functions'!$H$69)*(I11-'Elicitation of functions'!$H$69)+'Elicitation of functions'!$I$69,('Elicitation of functions'!$I$73-'Elicitation of functions'!$I$71)/('Elicitation of functions'!$H$73-'Elicitation of functions'!$H$71)*(I11-'Elicitation of functions'!$H$71)+'Elicitation of functions'!$I$71))) -> 0.5625 | T11: =INDEX('Elicitation of functions'!$K$79:$K$83,MATCH(J11,'Elicitation of functions'!$F$79:$F$83,0)) -> 0.35 | V11: 0.5 | W11: 0.75 | X11: 0.541667 | Y11: 0.5625 | Z11: 0.35
B12: Nordic-Baltic Tech Alliance | C12: 0.82 | D12: 0.75 | E12: Acceptable | F12: 1 | G12: Robust | H12: 0.65 | I12: 0.86 | J12: 4 | L12: =B12 -> Nordic-Baltic Tech Alliance | M12: =IF(C12<'Elicitation of functions'!$H$10,('Elicitation of functions'!$I$10-'Elicitation of functions'!$I$12)/('Elicitation of functions'!$H$10-'Elicitation of functions'!$H$12)*(C12-'Elicitation of functions'!$H$12)+'Elicitation of functions'!$I$12,IF(C12<'Elicitation of functions'!$H$9,('Elicitation of functions'!$I$9-'Elicitation of functions'!$I$10)/('Elicitation of functions'!$H$9-'Elicitation of functions'!$H$10)*(C12-'Elicitation of functions'!$H$10)+'Elicitation of functions'!$I$10,IF(C12<'Elicitation of functions'!$H$11,('Elicitation of functions'!$I$11-'Elicitation of functions'!$I$9)/('Elicitation of functions'!$H$11-'Elicitation of functions'!$H$9)*(C12-'Elicitation of functions'!$H$9)+'Elicitation of functions'!$I$9,('Elicitation of functions'!$I$13-'Elicitation of functions'!$I$11)/('Elicitation of functions'!$H$13-'Elicitation of functions'!$H$11)*(C12-'Elicitation of functions'!$H$11)+'Elicitation of functions'!$I$11))) -> 0.6 | N12: =IF(D12<'Elicitation of functions'!$H$20,('Elicitation of functions'!$I$20-'Elicitation of functions'!$I$22)/('Elicitation of functions'!$H$20-'Elicitation of functions'!$H$22)*(D12-'Elicitation of functions'!$H$22)+'Elicitation of functions'!$I$22,IF(D12<'Elicitation of functions'!$H$19,('Elicitation of functions'!$I$19-'Elicitation of functions'!$I$20)/('Elicitation of functions'!$H$19-'Elicitation of functions'!$H$20)*(D12-'Elicitation of functions'!$H$20)+'Elicitation of functions'!$I$20,IF(D12<'Elicitation of functions'!$H$21,('Elicitation of functions'!$I$21-'Elicitation of functions'!$I$19)/('Elicitation of functions'!$H$21-'Elicitation of functions'!$H$19)*(D12-'Elicitation of functions'!$H$19)+'Elicitation of functions'!$I$19,('Elicitation of functions'!$I$23-'Elicitation of functions'!$I$21)/('Elicitation of functions'!$H$23-'Elicitation of functions'!$H$21)*(D12-'Elicitation of functions'!$H$21)+'Elicitation of functions'!$I$21))) -> 0.59375 | O12: =INDEX('Elicitation of functions'!$K$29:$K$33,MATCH(E12,'Elicitation of functions'!$F$29:$F$33,0)) -> 0.4 | P12: =INDEX('Elicitation of functions'!$K$39:$K$43,MATCH(F12,'Elicitation of functions'!$F$39:$F$43,0)) -> 0.3 | Q12: =INDEX('Elicitation of functions'!$K$49:$K$52,MATCH(G12,'Elicitation of functions'!$F$49:$F$52,0)) -> 0.75 | R12: =IF(H12<'Elicitation of functions'!$H$60,('Elicitation of functions'!$I$60-'Elicitation of functions'!$I$62)/('Elicitation of functions'!$H$60-'Elicitation of functions'!$H$62)*(H12-'Elicitation of functions'!$H$62)+'Elicitation of functions'!$I$62,IF(H12<'Elicitation of functions'!$H$59,('Elicitation of functions'!$I$59-'Elicitation of functions'!$I$60)/('Elicitation of functions'!$H$59-'Elicitation of functions'!$H$60)*(H12-'Elicitation of functions'!$H$60)+'Elicitation of functions'!$I$60,IF(H12<'Elicitation of functions'!$H$61,('Elicitation of functions'!$I$61-'Elicitation of functions'!$I$59)/('Elicitation of functions'!$H$61-'Elicitation of functions'!$H$59)*(H12-'Elicitation of functions'!$H$59)+'Elicitation of functions'!$I$59,('Elicitation of functions'!$I$63-'Elicitation of functions'!$I$61)/('Elicitation of functions'!$H$63-'Elicitation of functions'!$H$61)*(H12-'Elicitation of functions'!$H$61)+'Elicitation of functions'!$I$61))) -> 0.66666667 | S12: =IF(I12<'Elicitation of functions'!$H$70,('Elicitation of functions'!$I$70-'Elicitation of functions'!$I$72)/('Elicitation of functions'!$H$70-'Elicitation of functions'!$H$72)*(I12-'Elicitation of functions'!$H$72)+'Elicitation of functions'!$I$72,IF(I12<'Elicitation of functions'!$H$69,('Elicitation of functions'!$I$69-'Elicitation of functions'!$I$70)/('Elicitation of functions'!$H$69-'Elicitation of functions'!$H$70)*(I12-'Elicitation of functions'!$H$70)+'Elicitation of functions'!$I$70,IF(I12<'Elicitation of functions'!$H$71,('Elicitation of functions'!$I$71-'Elicitation of functions'!$I$69)/('Elicitation of functions'!$H$71-'Elicitation of functions'!$H$69)*(I12-'Elicitation of functions'!$H$69)+'Elicitation of functions'!$I$69,('Elicitation of functions'!$I$73-'Elicitation of functions'!$I$71)/('Elicitation of functions'!$H$73-'Elicitation of functions'!$H$71)*(I12-'Elicitation of functions'!$H$71)+'Elicitation of functions'!$I$71))) -> 0.625 | T12: =INDEX('Elicitation of functions'!$K$79:$K$83,MATCH(J12,'Elicitation of functions'!$F$79:$F$83,0)) -> 0.7 | V12: 0.3 | W12: 0.75 | X12: 0.666667 | Y12: 0.625 | Z12: 0.7
B13: Scenario 2: Always-Learning Society | L13: Scenario 2: Always-Learning Society - Attribute-specific value scores
B14: Action | C14: Achievement of learning outcomes (65-95%) | D14: Completion and progression (55-90%) | E14: Learner experience and engagement | F14: Accessibility, flexibility and equity (0-4) | G14: Integrity of assessment | H14: Strategic control / autonomy (20-90%) | I14: External relevance and employability (65-95%) | J14: Global attractiveness / reputation (1-5) | L14: Action | M14: Achievement of learning outcomes (65-95%) | N14: Completion and progression (55-90%) | O14: Learner experience and engagement | P14: Accessibility, flexibility and equity (0-4) | Q14: Integrity of assessment | R14: Strategic control / autonomy (20-90%) | S14: External relevance and employability (65-95%) | T14: Global attractiveness / reputation (1-5)
B15: AI-Enabled Student Guidance | C15: 0.88 | D15: 0.85 | E15: Acceptable | F15: 4 | G15: Fragile | H15: 0.35 | I15: 0.85 | J15: 3 | L15: =B15 -> AI-Enabled Student Guidance | M15: =IF(C15<'Elicitation of functions'!$H$10,('Elicitation of functions'!$I$10-'Elicitation of functions'!$I$12)/('Elicitation of functions'!$H$10-'Elicitation of functions'!$H$12)*(C15-'Elicitation of functions'!$H$12)+'Elicitation of functions'!$I$12,IF(C15<'Elicitation of functions'!$H$9,('Elicitation of functions'!$I$9-'Elicitation of functions'!$I$10)/('Elicitation of functions'!$H$9-'Elicitation of functions'!$H$10)*(C15-'Elicitation of functions'!$H$10)+'Elicitation of functions'!$I$10,IF(C15<'Elicitation of functions'!$H$11,('Elicitation of functions'!$I$11-'Elicitation of functions'!$I$9)/('Elicitation of functions'!$H$11-'Elicitation of functions'!$H$9)*(C15-'Elicitation of functions'!$H$9)+'Elicitation of functions'!$I$9,('Elicitation of functions'!$I$13-'Elicitation of functions'!$I$11)/('Elicitation of functions'!$H$13-'Elicitation of functions'!$H$11)*(C15-'Elicitation of functions'!$H$11)+'Elicitation of functions'!$I$11))) -> 0.825 | N15: =IF(D15<'Elicitation of functions'!$H$20,('Elicitation of functions'!$I$20-'Elicitation of functions'!$I$22)/('Elicitation of functions'!$H$20-'Elicitation of functions'!$H$22)*(D15-'Elicitation of functions'!$H$22)+'Elicitation of functions'!$I$22,IF(D15<'Elicitation of functions'!$H$19,('Elicitation of functions'!$I$19-'Elicitation of functions'!$I$20)/('Elicitation of functions'!$H$19-'Elicitation of functions'!$H$20)*(D15-'Elicitation of functions'!$H$20)+'Elicitation of functions'!$I$20,IF(D15<'Elicitation of functions'!$H$21,('Elicitation of functions'!$I$21-'Elicitation of functions'!$I$19)/('Elicitation of functions'!$H$21-'Elicitation of functions'!$H$19)*(D15-'Elicitation of functions'!$H$19)+'Elicitation of functions'!$I$19,('Elicitation of functions'!$I$23-'Elicitation of functions'!$I$21)/('Elicitation of functions'!$H$23-'Elicitation of functions'!$H$21)*(D15-'Elicitation of functions'!$H$21)+'Elicitation of functions'!$I$21))) -> 0.875 | O15: =INDEX('Elicitation of functions'!$K$29:$K$33,MATCH(E15,'Elicitation of functions'!$F$29:$F$33,0)) -> 0.4 | P15: =INDEX('Elicitation of functions'!$K$39:$K$43,MATCH(F15,'Elicitation of functions'!$F$39:$F$43,0)) -> 1 | Q15: =INDEX('Elicitation of functions'!$K$49:$K$52,MATCH(G15,'Elicitation of functions'!$F$49:$F$52,0)) -> 0 | R15: =IF(H15<'Elicitation of functions'!$H$60,('Elicitation of functions'!$I$60-'Elicitation of functions'!$I$62)/('Elicitation of functions'!$H$60-'Elicitation of functions'!$H$62)*(H15-'Elicitation of functions'!$H$62)+'Elicitation of functions'!$I$62,IF(H15<'Elicitation of functions'!$H$59,('Elicitation of functions'!$I$59-'Elicitation of functions'!$I$60)/('Elicitation of functions'!$H$59-'Elicitation of functions'!$H$60)*(H15-'Elicitation of functions'!$H$60)+'Elicitation of functions'!$I$60,IF(H15<'Elicitation of functions'!$H$61,('Elicitation of functions'!$I$61-'Elicitation of functions'!$I$59)/('Elicitation of functions'!$H$61-'Elicitation of functions'!$H$59)*(H15-'Elicitation of functions'!$H$59)+'Elicitation of functions'!$I$59,('Elicitation of functions'!$I$63-'Elicitation of functions'!$I$61)/('Elicitation of functions'!$H$63-'Elicitation of functions'!$H$61)*(H15-'Elicitation of functions'!$H$61)+'Elicitation of functions'!$I$61))) -> 0.33333333 | S15: =IF(I15<'Elicitation of functions'!$H$70,('Elicitation of functions'!$I$70-'Elicitation of functions'!$I$72)/('Elicitation of functions'!$H$70-'Elicitation of functions'!$H$72)*(I15-'Elicitation of functions'!$H$72)+'Elicitation of functions'!$I$72,IF(I15<'Elicitation of functions'!$H$69,('Elicitation of functions'!$I$69-'Elicitation of functions'!$I$70)/('Elicitation of functions'!$H$69-'Elicitation of functions'!$H$70)*(I15-'Elicitation of functions'!$H$70)+'Elicitation of functions'!$I$70,IF(I15<'Elicitation of functions'!$H$71,('Elicitation of functions'!$I$71-'Elicitation of functions'!$I$69)/('Elicitation of functions'!$H$71-'Elicitation of functions'!$H$69)*(I15-'Elicitation of functions'!$H$69)+'Elicitation of functions'!$I$69,('Elicitation of functions'!$I$73-'Elicitation of functions'!$I$71)/('Elicitation of functions'!$H$73-'Elicitation of functions'!$H$71)*(I15-'Elicitation of functions'!$H$71)+'Elicitation of functions'!$I$71))) -> 0.59375 | T15: =INDEX('Elicitation of functions'!$K$79:$K$83,MATCH(J15,'Elicitation of functions'!$F$79:$F$83,0)) -> 0.35 | V15: 1 | W15: 0 | X15: 0.333333 | Y15: 0.59375 | Z15: 0.35
B16: Elite Mentor Network / Smart Work-Study | C16: 0.82 | D16: 0.8 | E16: Excellent | F16: 1 | G16: Robust | H16: 0.4 | I16: 0.95 | J16: 4 | L16: =B16 -> Elite Mentor Network / Smart Work-Study | M16: =IF(C16<'Elicitation of functions'!$H$10,('Elicitation of functions'!$I$10-'Elicitation of functions'!$I$12)/('Elicitation of functions'!$H$10-'Elicitation of functions'!$H$12)*(C16-'Elicitation of functions'!$H$12)+'Elicitation of functions'!$I$12,IF(C16<'Elicitation of functions'!$H$9,('Elicitation of functions'!$I$9-'Elicitation of functions'!$I$10)/('Elicitation of functions'!$H$9-'Elicitation of functions'!$H$10)*(C16-'Elicitation of functions'!$H$10)+'Elicitation of functions'!$I$10,IF(C16<'Elicitation of functions'!$H$11,('Elicitation of functions'!$I$11-'Elicitation of functions'!$I$9)/('Elicitation of functions'!$H$11-'Elicitation of functions'!$H$9)*(C16-'Elicitation of functions'!$H$9)+'Elicitation of functions'!$I$9,('Elicitation of functions'!$I$13-'Elicitation of functions'!$I$11)/('Elicitation of functions'!$H$13-'Elicitation of functions'!$H$11)*(C16-'Elicitation of functions'!$H$11)+'Elicitation of functions'!$I$11))) -> 0.6 | N16: =IF(D16<'Elicitation of functions'!$H$20,('Elicitation of functions'!$I$20-'Elicitation of functions'!$I$22)/('Elicitation of functions'!$H$20-'Elicitation of functions'!$H$22)*(D16-'Elicitation of functions'!$H$22)+'Elicitation of functions'!$I$22,IF(D16<'Elicitation of functions'!$H$19,('Elicitation of functions'!$I$19-'Elicitation of functions'!$I$20)/('Elicitation of functions'!$H$19-'Elicitation of functions'!$H$20)*(D16-'Elicitation of functions'!$H$20)+'Elicitation of functions'!$I$20,IF(D16<'Elicitation of functions'!$H$21,('Elicitation of functions'!$I$21-'Elicitation of functions'!$I$19)/('Elicitation of functions'!$H$21-'Elicitation of functions'!$H$19)*(D16-'Elicitation of functions'!$H$19)+'Elicitation of functions'!$I$19,('Elicitation of functions'!$I$23-'Elicitation of functions'!$I$21)/('Elicitation of functions'!$H$23-'Elicitation of functions'!$H$21)*(D16-'Elicitation of functions'!$H$21)+'Elicitation of functions'!$I$21))) -> 0.75 | O16: =INDEX('Elicitation of functions'!$K$29:$K$33,MATCH(E16,'Elicitation of functions'!$F$29:$F$33,0)) -> 1 | P16: =INDEX('Elicitation of functions'!$K$39:$K$43,MATCH(F16,'Elicitation of functions'!$F$39:$F$43,0)) -> 0.3 | Q16: =INDEX('Elicitation of functions'!$K$49:$K$52,MATCH(G16,'Elicitation of functions'!$F$49:$F$52,0)) -> 0.75 | R16: =IF(H16<'Elicitation of functions'!$H$60,('Elicitation of functions'!$I$60-'Elicitation of functions'!$I$62)/('Elicitation of functions'!$H$60-'Elicitation of functions'!$H$62)*(H16-'Elicitation of functions'!$H$62)+'Elicitation of functions'!$I$62,IF(H16<'Elicitation of functions'!$H$59,('Elicitation of functions'!$I$59-'Elicitation of functions'!$I$60)/('Elicitation of functions'!$H$59-'Elicitation of functions'!$H$60)*(H16-'Elicitation of functions'!$H$60)+'Elicitation of functions'!$I$60,IF(H16<'Elicitation of functions'!$H$61,('Elicitation of functions'!$I$61-'Elicitation of functions'!$I$59)/('Elicitation of functions'!$H$61-'Elicitation of functions'!$H$59)*(H16-'Elicitation of functions'!$H$59)+'Elicitation of functions'!$I$59,('Elicitation of functions'!$I$63-'Elicitation of functions'!$I$61)/('Elicitation of functions'!$H$63-'Elicitation of functions'!$H$61)*(H16-'Elicitation of functions'!$H$61)+'Elicitation of functions'!$I$61))) -> 0.41666667 | S16: =IF(I16<'Elicitation of functions'!$H$70,('Elicitation of functions'!$I$70-'Elicitation of functions'!$I$72)/('Elicitation of functions'!$H$70-'Elicitation of functions'!$H$72)*(I16-'Elicitation of functions'!$H$72)+'Elicitation of functions'!$I$72,IF(I16<'Elicitation of functions'!$H$69,('Elicitation of functions'!$I$69-'Elicitation of functions'!$I$70)/('Elicitation of functions'!$H$69-'Elicitation of functions'!$H$70)*(I16-'Elicitation of functions'!$H$70)+'Elicitation of functions'!$I$70,IF(I16<'Elicitation of functions'!$H$71,('Elicitation of functions'!$I$71-'Elicitation of functions'!$I$69)/('Elicitation of functions'!$H$71-'Elicitation of functions'!$H$69)*(I16-'Elicitation of functions'!$H$69)+'Elicitation of functions'!$I$69,('Elicitation of functions'!$I$73-'Elicitation of functions'!$I$71)/('Elicitation of functions'!$H$73-'Elicitation of functions'!$H$71)*(I16-'Elicitation of functions'!$H$71)+'Elicitation of functions'!$I$71))) -> 1 | T16: =INDEX('Elicitation of functions'!$K$79:$K$83,MATCH(J16,'Elicitation of functions'!$F$79:$F$83,0)) -> 0.7 | V16: 0.3 | W16: 0.75 | X16: 0.416667 | Y16: 1 | Z16: 0.7
B17: AI Governance Board / Assessment Integrity | C17: 0.78 | D17: 0.68 | E17: Poor | F17: 2 | G17: Exemplary | H17: 0.55 | I17: 0.82 | J17: 4 | L17: =B17 -> AI Governance Board / Assessment Integrity | M17: =IF(C17<'Elicitation of functions'!$H$10,('Elicitation of functions'!$I$10-'Elicitation of functions'!$I$12)/('Elicitation of functions'!$H$10-'Elicitation of functions'!$H$12)*(C17-'Elicitation of functions'!$H$12)+'Elicitation of functions'!$I$12,IF(C17<'Elicitation of functions'!$H$9,('Elicitation of functions'!$I$9-'Elicitation of functions'!$I$10)/('Elicitation of functions'!$H$9-'Elicitation of functions'!$H$10)*(C17-'Elicitation of functions'!$H$10)+'Elicitation of functions'!$I$10,IF(C17<'Elicitation of functions'!$H$11,('Elicitation of functions'!$I$11-'Elicitation of functions'!$I$9)/('Elicitation of functions'!$H$11-'Elicitation of functions'!$H$9)*(C17-'Elicitation of functions'!$H$9)+'Elicitation of functions'!$I$9,('Elicitation of functions'!$I$13-'Elicitation of functions'!$I$11)/('Elicitation of functions'!$H$13-'Elicitation of functions'!$H$11)*(C17-'Elicitation of functions'!$H$11)+'Elicitation of functions'!$I$11))) -> 0.4375 | N17: =IF(D17<'Elicitation of functions'!$H$20,('Elicitation of functions'!$I$20-'Elicitation of functions'!$I$22)/('Elicitation of functions'!$H$20-'Elicitation of functions'!$H$22)*(D17-'Elicitation of functions'!$H$22)+'Elicitation of functions'!$I$22,IF(D17<'Elicitation of functions'!$H$19,('Elicitation of functions'!$I$19-'Elicitation of functions'!$I$20)/('Elicitation of functions'!$H$19-'Elicitation of functions'!$H$20)*(D17-'Elicitation of functions'!$H$20)+'Elicitation of functions'!$I$20,IF(D17<'Elicitation of functions'!$H$21,('Elicitation of functions'!$I$21-'Elicitation of functions'!$I$19)/('Elicitation of functions'!$H$21-'Elicitation of functions'!$H$19)*(D17-'Elicitation of functions'!$H$19)+'Elicitation of functions'!$I$19,('Elicitation of functions'!$I$23-'Elicitation of functions'!$I$21)/('Elicitation of functions'!$H$23-'Elicitation of functions'!$H$21)*(D17-'Elicitation of functions'!$H$21)+'Elicitation of functions'!$I$21))) -> 0.35714286 | O17: =INDEX('Elicitation of functions'!$K$29:$K$33,MATCH(E17,'Elicitation of functions'!$F$29:$F$33,0)) -> 0.2 | P17: =INDEX('Elicitation of functions'!$K$39:$K$43,MATCH(F17,'Elicitation of functions'!$F$39:$F$43,0)) -> 0.5 | Q17: =INDEX('Elicitation of functions'!$K$49:$K$52,MATCH(G17,'Elicitation of functions'!$F$49:$F$52,0)) -> 1 | R17: =IF(H17<'Elicitation of functions'!$H$60,('Elicitation of functions'!$I$60-'Elicitation of functions'!$I$62)/('Elicitation of functions'!$H$60-'Elicitation of functions'!$H$62)*(H17-'Elicitation of functions'!$H$62)+'Elicitation of functions'!$I$62,IF(H17<'Elicitation of functions'!$H$59,('Elicitation of functions'!$I$59-'Elicitation of functions'!$I$60)/('Elicitation of functions'!$H$59-'Elicitation of functions'!$H$60)*(H17-'Elicitation of functions'!$H$60)+'Elicitation of functions'!$I$60,IF(H17<'Elicitation of functions'!$H$61,('Elicitation of functions'!$I$61-'Elicitation of functions'!$I$59)/('Elicitation of functions'!$H$61-'Elicitation of functions'!$H$59)*(H17-'Elicitation of functions'!$H$59)+'Elicitation of functions'!$I$59,('Elicitation of functions'!$I$63-'Elicitation of functions'!$I$61)/('Elicitation of functions'!$H$63-'Elicitation of functions'!$H$61)*(H17-'Elicitation of functions'!$H$61)+'Elicitation of functions'!$I$61))) -> 0.58333333 | S17: =IF(I17<'Elicitation of functions'!$H$70,('Elicitation of functions'!$I$70-'Elicitation of functions'!$I$72)/('Elicitation of functions'!$H$70-'Elicitation of functions'!$H$72)*(I17-'Elicitation of functions'!$H$72)+'Elicitation of functions'!$I$72,IF(I17<'Elicitation of functions'!$H$69,('Elicitation of functions'!$I$69-'Elicitation of functions'!$I$70)/('Elicitation of functions'!$H$69-'Elicitation of functions'!$H$70)*(I17-'Elicitation of functions'!$H$70)+'Elicitation of functions'!$I$70,IF(I17<'Elicitation of functions'!$H$71,('Elicitation of functions'!$I$71-'Elicitation of functions'!$I$69)/('Elicitation of functions'!$H$71-'Elicitation of functions'!$H$69)*(I17-'Elicitation of functions'!$H$69)+'Elicitation of functions'!$I$69,('Elicitation of functions'!$I$73-'Elicitation of functions'!$I$71)/('Elicitation of functions'!$H$73-'Elicitation of functions'!$H$71)*(I17-'Elicitation of functions'!$H$71)+'Elicitation of functions'!$I$71))) -> 0.5 | T17: =INDEX('Elicitation of functions'!$K$79:$K$83,MATCH(J17,'Elicitation of functions'!$F$79:$F$83,0)) -> 0.7 | V17: 0.5 | W17: 1 | X17: 0.583333 | Y17: 0.5 | Z17: 0.7
B18: Aalto-Controlled Core Infrastructure | C18: 0.82 | D18: 0.75 | E18: Poor | F18: 3 | G18: Robust | H18: 0.85 | I18: 0.85 | J18: 2 | L18: =B18 -> Aalto-Controlled Core Infrastructure | M18: =IF(C18<'Elicitation of functions'!$H$10,('Elicitation of functions'!$I$10-'Elicitation of functions'!$I$12)/('Elicitation of functions'!$H$10-'Elicitation of functions'!$H$12)*(C18-'Elicitation of functions'!$H$12)+'Elicitation of functions'!$I$12,IF(C18<'Elicitation of functions'!$H$9,('Elicitation of functions'!$I$9-'Elicitation of functions'!$I$10)/('Elicitation of functions'!$H$9-'Elicitation of functions'!$H$10)*(C18-'Elicitation of functions'!$H$10)+'Elicitation of functions'!$I$10,IF(C18<'Elicitation of functions'!$H$11,('Elicitation of functions'!$I$11-'Elicitation of functions'!$I$9)/('Elicitation of functions'!$H$11-'Elicitation of functions'!$H$9)*(C18-'Elicitation of functions'!$H$9)+'Elicitation of functions'!$I$9,('Elicitation of functions'!$I$13-'Elicitation of functions'!$I$11)/('Elicitation of functions'!$H$13-'Elicitation of functions'!$H$11)*(C18-'Elicitation of functions'!$H$11)+'Elicitation of functions'!$I$11))) -> 0.6 | N18: =IF(D18<'Elicitation of functions'!$H$20,('Elicitation of functions'!$I$20-'Elicitation of functions'!$I$22)/('Elicitation of functions'!$H$20-'Elicitation of functions'!$H$22)*(D18-'Elicitation of functions'!$H$22)+'Elicitation of functions'!$I$22,IF(D18<'Elicitation of functions'!$H$19,('Elicitation of functions'!$I$19-'Elicitation of functions'!$I$20)/('Elicitation of functions'!$H$19-'Elicitation of functions'!$H$20)*(D18-'Elicitation of functions'!$H$20)+'Elicitation of functions'!$I$20,IF(D18<'Elicitation of functions'!$H$21,('Elicitation of functions'!$I$21-'Elicitation of functions'!$I$19)/('Elicitation of functions'!$H$21-'Elicitation of functions'!$H$19)*(D18-'Elicitation of functions'!$H$19)+'Elicitation of functions'!$I$19,('Elicitation of functions'!$I$23-'Elicitation of functions'!$I$21)/('Elicitation of functions'!$H$23-'Elicitation of functions'!$H$21)*(D18-'Elicitation of functions'!$H$21)+'Elicitation of functions'!$I$21))) -> 0.59375 | O18: =INDEX('Elicitation of functions'!$K$29:$K$33,MATCH(E18,'Elicitation of functions'!$F$29:$F$33,0)) -> 0.2 | P18: =INDEX('Elicitation of functions'!$K$39:$K$43,MATCH(F18,'Elicitation of functions'!$F$39:$F$43,0)) -> 0.8 | Q18: =INDEX('Elicitation of functions'!$K$49:$K$52,MATCH(G18,'Elicitation of functions'!$F$49:$F$52,0)) -> 0.75 | R18: =IF(H18<'Elicitation of functions'!$H$60,('Elicitation of functions'!$I$60-'Elicitation of functions'!$I$62)/('Elicitation of functions'!$H$60-'Elicitation of functions'!$H$62)*(H18-'Elicitation of functions'!$H$62)+'Elicitation of functions'!$I$62,IF(H18<'Elicitation of functions'!$H$59,('Elicitation of functions'!$I$59-'Elicitation of functions'!$I$60)/('Elicitation of functions'!$H$59-'Elicitation of functions'!$H$60)*(H18-'Elicitation of functions'!$H$60)+'Elicitation of functions'!$I$60,IF(H18<'Elicitation of functions'!$H$61,('Elicitation of functions'!$I$61-'Elicitation of functions'!$I$59)/('Elicitation of functions'!$H$61-'Elicitation of functions'!$H$59)*(H18-'Elicitation of functions'!$H$59)+'Elicitation of functions'!$I$59,('Elicitation of functions'!$I$63-'Elicitation of functions'!$I$61)/('Elicitation of functions'!$H$63-'Elicitation of functions'!$H$61)*(H18-'Elicitation of functions'!$H$61)+'Elicitation of functions'!$I$61))) -> 0.91666667 | S18: =IF(I18<'Elicitation of functions'!$H$70,('Elicitation of functions'!$I$70-'Elicitation of functions'!$I$72)/('Elicitation of functions'!$H$70-'Elicitation of functions'!$H$72)*(I18-'Elicitation of functions'!$H$72)+'Elicitation of functions'!$I$72,IF(I18<'Elicitation of functions'!$H$69,('Elicitation of functions'!$I$69-'Elicitation of functions'!$I$70)/('Elicitation of functions'!$H$69-'Elicitation of functions'!$H$70)*(I18-'Elicitation of functions'!$H$70)+'Elicitation of functions'!$I$70,IF(I18<'Elicitation of functions'!$H$71,('Elicitation of functions'!$I$71-'Elicitation of functions'!$I$69)/('Elicitation of functions'!$H$71-'Elicitation of functions'!$H$69)*(I18-'Elicitation of functions'!$H$69)+'Elicitation of functions'!$I$69,('Elicitation of functions'!$I$73-'Elicitation of functions'!$I$71)/('Elicitation of functions'!$H$73-'Elicitation of functions'!$H$71)*(I18-'Elicitation of functions'!$H$71)+'Elicitation of functions'!$I$71))) -> 0.59375 | T18: =INDEX('Elicitation of functions'!$K$79:$K$83,MATCH(J18,'Elicitation of functions'!$F$79:$F$83,0)) -> 0.2 | V18: 0.8 | W18: 0.75 | X18: 0.916667 | Y18: 0.59375 | Z18: 0.2
B19: Aalto-Certified Micro-Credentials | C19: 0.85 | D19: 0.82 | E19: Good | F19: 4 | G19: Basic | H19: 0.45 | I19: 0.92 | J19: 4 | L19: =B19 -> Aalto-Certified Micro-Credentials | M19: =IF(C19<'Elicitation of functions'!$H$10,('Elicitation of functions'!$I$10-'Elicitation of functions'!$I$12)/('Elicitation of functions'!$H$10-'Elicitation of functions'!$H$12)*(C19-'Elicitation of functions'!$H$12)+'Elicitation of functions'!$I$12,IF(C19<'Elicitation of functions'!$H$9,('Elicitation of functions'!$I$9-'Elicitation of functions'!$I$10)/('Elicitation of functions'!$H$9-'Elicitation of functions'!$H$10)*(C19-'Elicitation of functions'!$H$10)+'Elicitation of functions'!$I$10,IF(C19<'Elicitation of functions'!$H$11,('Elicitation of functions'!$I$11-'Elicitation of functions'!$I$9)/('Elicitation of functions'!$H$11-'Elicitation of functions'!$H$9)*(C19-'Elicitation of functions'!$H$9)+'Elicitation of functions'!$I$9,('Elicitation of functions'!$I$13-'Elicitation of functions'!$I$11)/('Elicitation of functions'!$H$13-'Elicitation of functions'!$H$11)*(C19-'Elicitation of functions'!$H$11)+'Elicitation of functions'!$I$11))) -> 0.75 | N19: =IF(D19<'Elicitation of functions'!$H$20,('Elicitation of functions'!$I$20-'Elicitation of functions'!$I$22)/('Elicitation of functions'!$H$20-'Elicitation of functions'!$H$22)*(D19-'Elicitation of functions'!$H$22)+'Elicitation of functions'!$I$22,IF(D19<'Elicitation of functions'!$H$19,('Elicitation of functions'!$I$19-'Elicitation of functions'!$I$20)/('Elicitation of functions'!$H$19-'Elicitation of functions'!$H$20)*(D19-'Elicitation of functions'!$H$20)+'Elicitation of functions'!$I$20,IF(D19<'Elicitation of functions'!$H$21,('Elicitation of functions'!$I$21-'Elicitation of functions'!$I$19)/('Elicitation of functions'!$H$21-'Elicitation of functions'!$H$19)*(D19-'Elicitation of functions'!$H$19)+'Elicitation of functions'!$I$19,('Elicitation of functions'!$I$23-'Elicitation of functions'!$I$21)/('Elicitation of functions'!$H$23-'Elicitation of functions'!$H$21)*(D19-'Elicitation of functions'!$H$21)+'Elicitation of functions'!$I$21))) -> 0.8 | O19: =INDEX('Elicitation of functions'!$K$29:$K$33,MATCH(E19,'Elicitation of functions'!$F$29:$F$33,0)) -> 0.7 | P19: =INDEX('Elicitation of functions'!$K$39:$K$43,MATCH(F19,'Elicitation of functions'!$F$39:$F$43,0)) -> 1 | Q19: =INDEX('Elicitation of functions'!$K$49:$K$52,MATCH(G19,'Elicitation of functions'!$F$49:$F$52,0)) -> 0.5 | R19: =IF(H19<'Elicitation of functions'!$H$60,('Elicitation of functions'!$I$60-'Elicitation of functions'!$I$62)/('Elicitation of functions'!$H$60-'Elicitation of functions'!$H$62)*(H19-'Elicitation of functions'!$H$62)+'Elicitation of functions'!$I$62,IF(H19<'Elicitation of functions'!$H$59,('Elicitation of functions'!$I$59-'Elicitation of functions'!$I$60)/('Elicitation of functions'!$H$59-'Elicitation of functions'!$H$60)*(H19-'Elicitation of functions'!$H$60)+'Elicitation of functions'!$I$60,IF(H19<'Elicitation of functions'!$H$61,('Elicitation of functions'!$I$61-'Elicitation of functions'!$I$59)/('Elicitation of functions'!$H$61-'Elicitation of functions'!$H$59)*(H19-'Elicitation of functions'!$H$59)+'Elicitation of functions'!$I$59,('Elicitation of functions'!$I$63-'Elicitation of functions'!$I$61)/('Elicitation of functions'!$H$63-'Elicitation of functions'!$H$61)*(H19-'Elicitation of functions'!$H$61)+'Elicitation of functions'!$I$61))) -> 0.5 | S19: =IF(I19<'Elicitation of functions'!$H$70,('Elicitation of functions'!$I$70-'Elicitation of functions'!$I$72)/('Elicitation of functions'!$H$70-'Elicitation of functions'!$H$72)*(I19-'Elicitation of functions'!$H$72)+'Elicitation of functions'!$I$72,IF(I19<'Elicitation of functions'!$H$69,('Elicitation of functions'!$I$69-'Elicitation of functions'!$I$70)/('Elicitation of functions'!$H$69-'Elicitation of functions'!$H$70)*(I19-'Elicitation of functions'!$H$70)+'Elicitation of functions'!$I$70,IF(I19<'Elicitation of functions'!$H$71,('Elicitation of functions'!$I$71-'Elicitation of functions'!$I$69)/('Elicitation of functions'!$H$71-'Elicitation of functions'!$H$69)*(I19-'Elicitation of functions'!$H$69)+'Elicitation of functions'!$I$69,('Elicitation of functions'!$I$73-'Elicitation of functions'!$I$71)/('Elicitation of functions'!$H$73-'Elicitation of functions'!$H$71)*(I19-'Elicitation of functions'!$H$71)+'Elicitation of functions'!$I$71))) -> 0.85 | T19: =INDEX('Elicitation of functions'!$K$79:$K$83,MATCH(J19,'Elicitation of functions'!$F$79:$F$83,0)) -> 0.7 | V19: 1 | W19: 0.5 | X19: 0.5 | Y19: 0.85 | Z19: 0.7
B20: Pedagogical Training for Staff | C20: 0.88 | D20: 0.8 | E20: Good | F20: 3 | G20: Robust | H20: 0.45 | I20: 0.85 | J20: 3 | L20: =B20 -> Pedagogical Training for Staff | M20: =IF(C20<'Elicitation of functions'!$H$10,('Elicitation of functions'!$I$10-'Elicitation of functions'!$I$12)/('Elicitation of functions'!$H$10-'Elicitation of functions'!$H$12)*(C20-'Elicitation of functions'!$H$12)+'Elicitation of functions'!$I$12,IF(C20<'Elicitation of functions'!$H$9,('Elicitation of functions'!$I$9-'Elicitation of functions'!$I$10)/('Elicitation of functions'!$H$9-'Elicitation of functions'!$H$10)*(C20-'Elicitation of functions'!$H$10)+'Elicitation of functions'!$I$10,IF(C20<'Elicitation of functions'!$H$11,('Elicitation of functions'!$I$11-'Elicitation of functions'!$I$9)/('Elicitation of functions'!$H$11-'Elicitation of functions'!$H$9)*(C20-'Elicitation of functions'!$H$9)+'Elicitation of functions'!$I$9,('Elicitation of functions'!$I$13-'Elicitation of functions'!$I$11)/('Elicitation of functions'!$H$13-'Elicitation of functions'!$H$11)*(C20-'Elicitation of functions'!$H$11)+'Elicitation of functions'!$I$11))) -> 0.825 | N20: =IF(D20<'Elicitation of functions'!$H$20,('Elicitation of functions'!$I$20-'Elicitation of functions'!$I$22)/('Elicitation of functions'!$H$20-'Elicitation of functions'!$H$22)*(D20-'Elicitation of functions'!$H$22)+'Elicitation of functions'!$I$22,IF(D20<'Elicitation of functions'!$H$19,('Elicitation of functions'!$I$19-'Elicitation of functions'!$I$20)/('Elicitation of functions'!$H$19-'Elicitation of functions'!$H$20)*(D20-'Elicitation of functions'!$H$20)+'Elicitation of functions'!$I$20,IF(D20<'Elicitation of functions'!$H$21,('Elicitation of functions'!$I$21-'Elicitation of functions'!$I$19)/('Elicitation of functions'!$H$21-'Elicitation of functions'!$H$19)*(D20-'Elicitation of functions'!$H$19)+'Elicitation of functions'!$I$19,('Elicitation of functions'!$I$23-'Elicitation of functions'!$I$21)/('Elicitation of functions'!$H$23-'Elicitation of functions'!$H$21)*(D20-'Elicitation of functions'!$H$21)+'Elicitation of functions'!$I$21))) -> 0.75 | O20: =INDEX('Elicitation of functions'!$K$29:$K$33,MATCH(E20,'Elicitation of functions'!$F$29:$F$33,0)) -> 0.7 | P20: =INDEX('Elicitation of functions'!$K$39:$K$43,MATCH(F20,'Elicitation of functions'!$F$39:$F$43,0)) -> 0.8 | Q20: =INDEX('Elicitation of functions'!$K$49:$K$52,MATCH(G20,'Elicitation of functions'!$F$49:$F$52,0)) -> 0.75 | R20: =IF(H20<'Elicitation of functions'!$H$60,('Elicitation of functions'!$I$60-'Elicitation of functions'!$I$62)/('Elicitation of functions'!$H$60-'Elicitation of functions'!$H$62)*(H20-'Elicitation of functions'!$H$62)+'Elicitation of functions'!$I$62,IF(H20<'Elicitation of functions'!$H$59,('Elicitation of functions'!$I$59-'Elicitation of functions'!$I$60)/('Elicitation of functions'!$H$59-'Elicitation of functions'!$H$60)*(H20-'Elicitation of functions'!$H$60)+'Elicitation of functions'!$I$60,IF(H20<'Elicitation of functions'!$H$61,('Elicitation of functions'!$I$61-'Elicitation of functions'!$I$59)/('Elicitation of functions'!$H$61-'Elicitation of functions'!$H$59)*(H20-'Elicitation of functions'!$H$59)+'Elicitation of functions'!$I$59,('Elicitation of functions'!$I$63-'Elicitation of functions'!$I$61)/('Elicitation of functions'!$H$63-'Elicitation of functions'!$H$61)*(H20-'Elicitation of functions'!$H$61)+'Elicitation of functions'!$I$61))) -> 0.5 | S20: =IF(I20<'Elicitation of functions'!$H$70,('Elicitation of functions'!$I$70-'Elicitation of functions'!$I$72)/('Elicitation of functions'!$H$70-'Elicitation of functions'!$H$72)*(I20-'Elicitation of functions'!$H$72)+'Elicitation of functions'!$I$72,IF(I20<'Elicitation of functions'!$H$69,('Elicitation of functions'!$I$69-'Elicitation of functions'!$I$70)/('Elicitation of functions'!$H$69-'Elicitation of functions'!$H$70)*(I20-'Elicitation of functions'!$H$70)+'Elicitation of functions'!$I$70,IF(I20<'Elicitation of functions'!$H$71,('Elicitation of functions'!$I$71-'Elicitation of functions'!$I$69)/('Elicitation of functions'!$H$71-'Elicitation of functions'!$H$69)*(I20-'Elicitation of functions'!$H$69)+'Elicitation of functions'!$I$69,('Elicitation of functions'!$I$73-'Elicitation of functions'!$I$71)/('Elicitation of functions'!$H$73-'Elicitation of functions'!$H$71)*(I20-'Elicitation of functions'!$H$71)+'Elicitation of functions'!$I$71))) -> 0.59375 | T20: =INDEX('Elicitation of functions'!$K$79:$K$83,MATCH(J20,'Elicitation of functions'!$F$79:$F$83,0)) -> 0.35 | V20: 0.8 | W20: 0.75 | X20: 0.5 | Y20: 0.59375 | Z20: 0.35
B21: Nordic-Baltic Tech Alliance | C21: 0.8 | D21: 0.72 | E21: Acceptable | F21: 2 | G21: Robust | H21: 0.55 | I21: 0.88 | J21: 3 | L21: =B21 -> Nordic-Baltic Tech Alliance | M21: =IF(C21<'Elicitation of functions'!$H$10,('Elicitation of functions'!$I$10-'Elicitation of functions'!$I$12)/('Elicitation of functions'!$H$10-'Elicitation of functions'!$H$12)*(C21-'Elicitation of functions'!$H$12)+'Elicitation of functions'!$I$12,IF(C21<'Elicitation of functions'!$H$9,('Elicitation of functions'!$I$9-'Elicitation of functions'!$I$10)/('Elicitation of functions'!$H$9-'Elicitation of functions'!$H$10)*(C21-'Elicitation of functions'!$H$10)+'Elicitation of functions'!$I$10,IF(C21<'Elicitation of functions'!$H$11,('Elicitation of functions'!$I$11-'Elicitation of functions'!$I$9)/('Elicitation of functions'!$H$11-'Elicitation of functions'!$H$9)*(C21-'Elicitation of functions'!$H$9)+'Elicitation of functions'!$I$9,('Elicitation of functions'!$I$13-'Elicitation of functions'!$I$11)/('Elicitation of functions'!$H$13-'Elicitation of functions'!$H$11)*(C21-'Elicitation of functions'!$H$11)+'Elicitation of functions'!$I$11))) -> 0.5 | N21: =IF(D21<'Elicitation of functions'!$H$20,('Elicitation of functions'!$I$20-'Elicitation of functions'!$I$22)/('Elicitation of functions'!$H$20-'Elicitation of functions'!$H$22)*(D21-'Elicitation of functions'!$H$22)+'Elicitation of functions'!$I$22,IF(D21<'Elicitation of functions'!$H$19,('Elicitation of functions'!$I$19-'Elicitation of functions'!$I$20)/('Elicitation of functions'!$H$19-'Elicitation of functions'!$H$20)*(D21-'Elicitation of functions'!$H$20)+'Elicitation of functions'!$I$20,IF(D21<'Elicitation of functions'!$H$21,('Elicitation of functions'!$I$21-'Elicitation of functions'!$I$19)/('Elicitation of functions'!$H$21-'Elicitation of functions'!$H$19)*(D21-'Elicitation of functions'!$H$19)+'Elicitation of functions'!$I$19,('Elicitation of functions'!$I$23-'Elicitation of functions'!$I$21)/('Elicitation of functions'!$H$23-'Elicitation of functions'!$H$21)*(D21-'Elicitation of functions'!$H$21)+'Elicitation of functions'!$I$21))) -> 0.5 | O21: =INDEX('Elicitation of functions'!$K$29:$K$33,MATCH(E21,'Elicitation of functions'!$F$29:$F$33,0)) -> 0.4 | P21: =INDEX('Elicitation of functions'!$K$39:$K$43,MATCH(F21,'Elicitation of functions'!$F$39:$F$43,0)) -> 0.5 | Q21: =INDEX('Elicitation of functions'!$K$49:$K$52,MATCH(G21,'Elicitation of functions'!$F$49:$F$52,0)) -> 0.75 | R21: =IF(H21<'Elicitation of functions'!$H$60,('Elicitation of functions'!$I$60-'Elicitation of functions'!$I$62)/('Elicitation of functions'!$H$60-'Elicitation of functions'!$H$62)*(H21-'Elicitation of functions'!$H$62)+'Elicitation of functions'!$I$62,IF(H21<'Elicitation of functions'!$H$59,('Elicitation of functions'!$I$59-'Elicitation of functions'!$I$60)/('Elicitation of functions'!$H$59-'Elicitation of functions'!$H$60)*(H21-'Elicitation of functions'!$H$60)+'Elicitation of functions'!$I$60,IF(H21<'Elicitation of functions'!$H$61,('Elicitation of functions'!$I$61-'Elicitation of functions'!$I$59)/('Elicitation of functions'!$H$61-'Elicitation of functions'!$H$59)*(H21-'Elicitation of functions'!$H$59)+'Elicitation of functions'!$I$59,('Elicitation of functions'!$I$63-'Elicitation of functions'!$I$61)/('Elicitation of functions'!$H$63-'Elicitation of functions'!$H$61)*(H21-'Elicitation of functions'!$H$61)+'Elicitation of functions'!$I$61))) -> 0.58333333 | S21: =IF(I21<'Elicitation of functions'!$H$70,('Elicitation of functions'!$I$70-'Elicitation of functions'!$I$72)/('Elicitation of functions'!$H$70-'Elicitation of functions'!$H$72)*(I21-'Elicitation of functions'!$H$72)+'Elicitation of functions'!$I$72,IF(I21<'Elicitation of functions'!$H$69,('Elicitation of functions'!$I$69-'Elicitation of functions'!$I$70)/('Elicitation of functions'!$H$69-'Elicitation of functions'!$H$70)*(I21-'Elicitation of functions'!$H$70)+'Elicitation of functions'!$I$70,IF(I21<'Elicitation of functions'!$H$71,('Elicitation of functions'!$I$71-'Elicitation of functions'!$I$69)/('Elicitation of functions'!$H$71-'Elicitation of functions'!$H$69)*(I21-'Elicitation of functions'!$H$69)+'Elicitation of functions'!$I$69,('Elicitation of functions'!$I$73-'Elicitation of functions'!$I$71)/('Elicitation of functions'!$H$73-'Elicitation of functions'!$H$71)*(I21-'Elicitation of functions'!$H$71)+'Elicitation of functions'!$I$71))) -> 0.6875 | T21: =INDEX('Elicitation of functions'!$K$79:$K$83,MATCH(J21,'Elicitation of functions'!$F$79:$F$83,0)) -> 0.35 | V21: 0.5 | W21: 0.75 | X21: 0.583333 | Y21: 0.6875 | Z21: 0.35
B22: Scenario 3: Human-First University | L22: Scenario 3: Human-First University - Attribute-specific value scores
B23: Action | C23: Achievement of learning outcomes (65-95%) | D23: Completion and progression (55-90%) | E23: Learner experience and engagement | F23: Accessibility, flexibility and equity (0-4) | G23: Integrity of assessment | H23: Strategic control / autonomy (20-90%) | I23: External relevance and employability (65-95%) | J23: Global attractiveness / reputation (1-5) | L23: Action | M23: Achievement of learning outcomes (65-95%) | N23: Completion and progression (55-90%) | O23: Learner experience and engagement | P23: Accessibility, flexibility and equity (0-4) | Q23: Integrity of assessment | R23: Strategic control / autonomy (20-90%) | S23: External relevance and employability (65-95%) | T23: Global attractiveness / reputation (1-5)
B24: AI-Enabled Student Guidance | C24: 0.8 | D24: 0.75 | E24: Very poor | F24: 2 | G24: Fragile | H24: 0.45 | I24: 0.8 | J24: 2 | L24: =B24 -> AI-Enabled Student Guidance | M24: =IF(C24<'Elicitation of functions'!$H$10,('Elicitation of functions'!$I$10-'Elicitation of functions'!$I$12)/('Elicitation of functions'!$H$10-'Elicitation of functions'!$H$12)*(C24-'Elicitation of functions'!$H$12)+'Elicitation of functions'!$I$12,IF(C24<'Elicitation of functions'!$H$9,('Elicitation of functions'!$I$9-'Elicitation of functions'!$I$10)/('Elicitation of functions'!$H$9-'Elicitation of functions'!$H$10)*(C24-'Elicitation of functions'!$H$10)+'Elicitation of functions'!$I$10,IF(C24<'Elicitation of functions'!$H$11,('Elicitation of functions'!$I$11-'Elicitation of functions'!$I$9)/('Elicitation of functions'!$H$11-'Elicitation of functions'!$H$9)*(C24-'Elicitation of functions'!$H$9)+'Elicitation of functions'!$I$9,('Elicitation of functions'!$I$13-'Elicitation of functions'!$I$11)/('Elicitation of functions'!$H$13-'Elicitation of functions'!$H$11)*(C24-'Elicitation of functions'!$H$11)+'Elicitation of functions'!$I$11))) -> 0.5 | N24: =IF(D24<'Elicitation of functions'!$H$20,('Elicitation of functions'!$I$20-'Elicitation of functions'!$I$22)/('Elicitation of functions'!$H$20-'Elicitation of functions'!$H$22)*(D24-'Elicitation of functions'!$H$22)+'Elicitation of functions'!$I$22,IF(D24<'Elicitation of functions'!$H$19,('Elicitation of functions'!$I$19-'Elicitation of functions'!$I$20)/('Elicitation of functions'!$H$19-'Elicitation of functions'!$H$20)*(D24-'Elicitation of functions'!$H$20)+'Elicitation of functions'!$I$20,IF(D24<'Elicitation of functions'!$H$21,('Elicitation of functions'!$I$21-'Elicitation of functions'!$I$19)/('Elicitation of functions'!$H$21-'Elicitation of functions'!$H$19)*(D24-'Elicitation of functions'!$H$19)+'Elicitation of functions'!$I$19,('Elicitation of functions'!$I$23-'Elicitation of functions'!$I$21)/('Elicitation of functions'!$H$23-'Elicitation of functions'!$H$21)*(D24-'Elicitation of functions'!$H$21)+'Elicitation of functions'!$I$21))) -> 0.59375 | O24: =INDEX('Elicitation of functions'!$K$29:$K$33,MATCH(E24,'Elicitation of functions'!$F$29:$F$33,0)) -> 0 | P24: =INDEX('Elicitation of functions'!$K$39:$K$43,MATCH(F24,'Elicitation of functions'!$F$39:$F$43,0)) -> 0.5 | Q24: =INDEX('Elicitation of functions'!$K$49:$K$52,MATCH(G24,'Elicitation of functions'!$F$49:$F$52,0)) -> 0 | R24: =IF(H24<'Elicitation of functions'!$H$60,('Elicitation of functions'!$I$60-'Elicitation of functions'!$I$62)/('Elicitation of functions'!$H$60-'Elicitation of functions'!$H$62)*(H24-'Elicitation of functions'!$H$62)+'Elicitation of functions'!$I$62,IF(H24<'Elicitation of functions'!$H$59,('Elicitation of functions'!$I$59-'Elicitation of functions'!$I$60)/('Elicitation of functions'!$H$59-'Elicitation of functions'!$H$60)*(H24-'Elicitation of functions'!$H$60)+'Elicitation of functions'!$I$60,IF(H24<'Elicitation of functions'!$H$61,('Elicitation of functions'!$I$61-'Elicitation of functions'!$I$59)/('Elicitation of functions'!$H$61-'Elicitation of functions'!$H$59)*(H24-'Elicitation of functions'!$H$59)+'Elicitation of functions'!$I$59,('Elicitation of functions'!$I$63-'Elicitation of functions'!$I$61)/('Elicitation of functions'!$H$63-'Elicitation of functions'!$H$61)*(H24-'Elicitation of functions'!$H$61)+'Elicitation of functions'!$I$61))) -> 0.5 | S24: =IF(I24<'Elicitation of functions'!$H$70,('Elicitation of functions'!$I$70-'Elicitation of functions'!$I$72)/('Elicitation of functions'!$H$70-'Elicitation of functions'!$H$72)*(I24-'Elicitation of functions'!$H$72)+'Elicitation of functions'!$I$72,IF(I24<'Elicitation of functions'!$H$69,('Elicitation of functions'!$I$69-'Elicitation of functions'!$I$70)/('Elicitation of functions'!$H$69-'Elicitation of functions'!$H$70)*(I24-'Elicitation of functions'!$H$70)+'Elicitation of functions'!$I$70,IF(I24<'Elicitation of functions'!$H$71,('Elicitation of functions'!$I$71-'Elicitation of functions'!$I$69)/('Elicitation of functions'!$H$71-'Elicitation of functions'!$H$69)*(I24-'Elicitation of functions'!$H$69)+'Elicitation of functions'!$I$69,('Elicitation of functions'!$I$73-'Elicitation of functions'!$I$71)/('Elicitation of functions'!$H$73-'Elicitation of functions'!$H$71)*(I24-'Elicitation of functions'!$H$71)+'Elicitation of functions'!$I$71))) -> 0.45454545 | T24: =INDEX('Elicitation of functions'!$K$79:$K$83,MATCH(J24,'Elicitation of functions'!$F$79:$F$83,0)) -> 0.2 | V24: 0.5 | W24: 0 | X24: 0.5 | Y24: 0.454545 | Z24: 0.2
B25: Elite Mentor Network / Smart Work-Study | C25: 0.8 | D25: 0.72 | E25: Good | F25: 0 | G25: Robust | H25: 0.5 | I25: 0.88 | J25: 3 | L25: =B25 -> Elite Mentor Network / Smart Work-Study | M25: =IF(C25<'Elicitation of functions'!$H$10,('Elicitation of functions'!$I$10-'Elicitation of functions'!$I$12)/('Elicitation of functions'!$H$10-'Elicitation of functions'!$H$12)*(C25-'Elicitation of functions'!$H$12)+'Elicitation of functions'!$I$12,IF(C25<'Elicitation of functions'!$H$9,('Elicitation of functions'!$I$9-'Elicitation of functions'!$I$10)/('Elicitation of functions'!$H$9-'Elicitation of functions'!$H$10)*(C25-'Elicitation of functions'!$H$10)+'Elicitation of functions'!$I$10,IF(C25<'Elicitation of functions'!$H$11,('Elicitation of functions'!$I$11-'Elicitation of functions'!$I$9)/('Elicitation of functions'!$H$11-'Elicitation of functions'!$H$9)*(C25-'Elicitation of functions'!$H$9)+'Elicitation of functions'!$I$9,('Elicitation of functions'!$I$13-'Elicitation of functions'!$I$11)/('Elicitation of functions'!$H$13-'Elicitation of functions'!$H$11)*(C25-'Elicitation of functions'!$H$11)+'Elicitation of functions'!$I$11))) -> 0.5 | N25: =IF(D25<'Elicitation of functions'!$H$20,('Elicitation of functions'!$I$20-'Elicitation of functions'!$I$22)/('Elicitation of functions'!$H$20-'Elicitation of functions'!$H$22)*(D25-'Elicitation of functions'!$H$22)+'Elicitation of functions'!$I$22,IF(D25<'Elicitation of functions'!$H$19,('Elicitation of functions'!$I$19-'Elicitation of functions'!$I$20)/('Elicitation of functions'!$H$19-'Elicitation of functions'!$H$20)*(D25-'Elicitation of functions'!$H$20)+'Elicitation of functions'!$I$20,IF(D25<'Elicitation of functions'!$H$21,('Elicitation of functions'!$I$21-'Elicitation of functions'!$I$19)/('Elicitation of functions'!$H$21-'Elicitation of functions'!$H$19)*(D25-'Elicitation of functions'!$H$19)+'Elicitation of functions'!$I$19,('Elicitation of functions'!$I$23-'Elicitation of functions'!$I$21)/('Elicitation of functions'!$H$23-'Elicitation of functions'!$H$21)*(D25-'Elicitation of functions'!$H$21)+'Elicitation of functions'!$I$21))) -> 0.5 | O25: =INDEX('Elicitation of functions'!$K$29:$K$33,MATCH(E25,'Elicitation of functions'!$F$29:$F$33,0)) -> 0.7 | P25: =INDEX('Elicitation of functions'!$K$39:$K$43,MATCH(F25,'Elicitation of functions'!$F$39:$F$43,0)) -> 0 | Q25: =INDEX('Elicitation of functions'!$K$49:$K$52,MATCH(G25,'Elicitation of functions'!$F$49:$F$52,0)) -> 0.75 | R25: =IF(H25<'Elicitation of functions'!$H$60,('Elicitation of functions'!$I$60-'Elicitation of functions'!$I$62)/('Elicitation of functions'!$H$60-'Elicitation of functions'!$H$62)*(H25-'Elicitation of functions'!$H$62)+'Elicitation of functions'!$I$62,IF(H25<'Elicitation of functions'!$H$59,('Elicitation of functions'!$I$59-'Elicitation of functions'!$I$60)/('Elicitation of functions'!$H$59-'Elicitation of functions'!$H$60)*(H25-'Elicitation of functions'!$H$60)+'Elicitation of functions'!$I$60,IF(H25<'Elicitation of functions'!$H$61,('Elicitation of functions'!$I$61-'Elicitation of functions'!$I$59)/('Elicitation of functions'!$H$61-'Elicitation of functions'!$H$59)*(H25-'Elicitation of functions'!$H$59)+'Elicitation of functions'!$I$59,('Elicitation of functions'!$I$63-'Elicitation of functions'!$I$61)/('Elicitation of functions'!$H$63-'Elicitation of functions'!$H$61)*(H25-'Elicitation of functions'!$H$61)+'Elicitation of functions'!$I$61))) -> 0.54166667 | S25: =IF(I25<'Elicitation of functions'!$H$70,('Elicitation of functions'!$I$70-'Elicitation of functions'!$I$72)/('Elicitation of functions'!$H$70-'Elicitation of functions'!$H$72)*(I25-'Elicitation of functions'!$H$72)+'Elicitation of functions'!$I$72,IF(I25<'Elicitation of functions'!$H$69,('Elicitation of functions'!$I$69-'Elicitation of functions'!$I$70)/('Elicitation of functions'!$H$69-'Elicitation of functions'!$H$70)*(I25-'Elicitation of functions'!$H$70)+'Elicitation of functions'!$I$70,IF(I25<'Elicitation of functions'!$H$71,('Elicitation of functions'!$I$71-'Elicitation of functions'!$I$69)/('Elicitation of functions'!$H$71-'Elicitation of functions'!$H$69)*(I25-'Elicitation of functions'!$H$69)+'Elicitation of functions'!$I$69,('Elicitation of functions'!$I$73-'Elicitation of functions'!$I$71)/('Elicitation of functions'!$H$73-'Elicitation of functions'!$H$71)*(I25-'Elicitation of functions'!$H$71)+'Elicitation of functions'!$I$71))) -> 0.6875 | T25: =INDEX('Elicitation of functions'!$K$79:$K$83,MATCH(J25,'Elicitation of functions'!$F$79:$F$83,0)) -> 0.35 | V25: 0 | W25: 0.75 | X25: 0.541667 | Y25: 0.6875 | Z25: 0.35
B26: AI Governance Board / Assessment Integrity | C26: 0.75 | D26: 0.65 | E26: Acceptable | F26: 1 | G26: Exemplary | H26: 0.75 | I26: 0.78 | J26: 4 | L26: =B26 -> AI Governance Board / Assessment Integrity | M26: =IF(C26<'Elicitation of functions'!$H$10,('Elicitation of functions'!$I$10-'Elicitation of functions'!$I$12)/('Elicitation of functions'!$H$10-'Elicitation of functions'!$H$12)*(C26-'Elicitation of functions'!$H$12)+'Elicitation of functions'!$I$12,IF(C26<'Elicitation of functions'!$H$9,('Elicitation of functions'!$I$9-'Elicitation of functions'!$I$10)/('Elicitation of functions'!$H$9-'Elicitation of functions'!$H$10)*(C26-'Elicitation of functions'!$H$10)+'Elicitation of functions'!$I$10,IF(C26<'Elicitation of functions'!$H$11,('Elicitation of functions'!$I$11-'Elicitation of functions'!$I$9)/('Elicitation of functions'!$H$11-'Elicitation of functions'!$H$9)*(C26-'Elicitation of functions'!$H$9)+'Elicitation of functions'!$I$9,('Elicitation of functions'!$I$13-'Elicitation of functions'!$I$11)/('Elicitation of functions'!$H$13-'Elicitation of functions'!$H$11)*(C26-'Elicitation of functions'!$H$11)+'Elicitation of functions'!$I$11))) -> 0.34375 | N26: =IF(D26<'Elicitation of functions'!$H$20,('Elicitation of functions'!$I$20-'Elicitation of functions'!$I$22)/('Elicitation of functions'!$H$20-'Elicitation of functions'!$H$22)*(D26-'Elicitation of functions'!$H$22)+'Elicitation of functions'!$I$22,IF(D26<'Elicitation of functions'!$H$19,('Elicitation of functions'!$I$19-'Elicitation of functions'!$I$20)/('Elicitation of functions'!$H$19-'Elicitation of functions'!$H$20)*(D26-'Elicitation of functions'!$H$20)+'Elicitation of functions'!$I$20,IF(D26<'Elicitation of functions'!$H$21,('Elicitation of functions'!$I$21-'Elicitation of functions'!$I$19)/('Elicitation of functions'!$H$21-'Elicitation of functions'!$H$19)*(D26-'Elicitation of functions'!$H$19)+'Elicitation of functions'!$I$19,('Elicitation of functions'!$I$23-'Elicitation of functions'!$I$21)/('Elicitation of functions'!$H$23-'Elicitation of functions'!$H$21)*(D26-'Elicitation of functions'!$H$21)+'Elicitation of functions'!$I$21))) -> 0.25 | O26: =INDEX('Elicitation of functions'!$K$29:$K$33,MATCH(E26,'Elicitation of functions'!$F$29:$F$33,0)) -> 0.4 | P26: =INDEX('Elicitation of functions'!$K$39:$K$43,MATCH(F26,'Elicitation of functions'!$F$39:$F$43,0)) -> 0.3 | Q26: =INDEX('Elicitation of functions'!$K$49:$K$52,MATCH(G26,'Elicitation of functions'!$F$49:$F$52,0)) -> 1 | R26: =IF(H26<'Elicitation of functions'!$H$60,('Elicitation of functions'!$I$60-'Elicitation of functions'!$I$62)/('Elicitation of functions'!$H$60-'Elicitation of functions'!$H$62)*(H26-'Elicitation of functions'!$H$62)+'Elicitation of functions'!$I$62,IF(H26<'Elicitation of functions'!$H$59,('Elicitation of functions'!$I$59-'Elicitation of functions'!$I$60)/('Elicitation of functions'!$H$59-'Elicitation of functions'!$H$60)*(H26-'Elicitation of functions'!$H$60)+'Elicitation of functions'!$I$60,IF(H26<'Elicitation of functions'!$H$61,('Elicitation of functions'!$I$61-'Elicitation of functions'!$I$59)/('Elicitation of functions'!$H$61-'Elicitation of functions'!$H$59)*(H26-'Elicitation of functions'!$H$59)+'Elicitation of functions'!$I$59,('Elicitation of functions'!$I$63-'Elicitation of functions'!$I$61)/('Elicitation of functions'!$H$63-'Elicitation of functions'!$H$61)*(H26-'Elicitation of functions'!$H$61)+'Elicitation of functions'!$I$61))) -> 0.75 | S26: =IF(I26<'Elicitation of functions'!$H$70,('Elicitation of functions'!$I$70-'Elicitation of functions'!$I$72)/('Elicitation of functions'!$H$70-'Elicitation of functions'!$H$72)*(I26-'Elicitation of functions'!$H$72)+'Elicitation of functions'!$I$72,IF(I26<'Elicitation of functions'!$H$69,('Elicitation of functions'!$I$69-'Elicitation of functions'!$I$70)/('Elicitation of functions'!$H$69-'Elicitation of functions'!$H$70)*(I26-'Elicitation of functions'!$H$70)+'Elicitation of functions'!$I$70,IF(I26<'Elicitation of functions'!$H$71,('Elicitation of functions'!$I$71-'Elicitation of functions'!$I$69)/('Elicitation of functions'!$H$71-'Elicitation of functions'!$H$69)*(I26-'Elicitation of functions'!$H$69)+'Elicitation of functions'!$I$69,('Elicitation of functions'!$I$73-'Elicitation of functions'!$I$71)/('Elicitation of functions'!$H$73-'Elicitation of functions'!$H$71)*(I26-'Elicitation of functions'!$H$71)+'Elicitation of functions'!$I$71))) -> 0.40909091 | T26: =INDEX('Elicitation of functions'!$K$79:$K$83,MATCH(J26,'Elicitation of functions'!$F$79:$F$83,0)) -> 0.7 | V26: 0.3 | W26: 1 | X26: 0.75 | Y26: 0.409091 | Z26: 0.7
B27: Aalto-Controlled Core Infrastructure | C27: 0.78 | D27: 0.7 | E27: Acceptable | F27: 1 | G27: Exemplary | H27: 0.9 | I27: 0.8 | J27: 3 | L27: =B27 -> Aalto-Controlled Core Infrastructure | M27: =IF(C27<'Elicitation of functions'!$H$10,('Elicitation of functions'!$I$10-'Elicitation of functions'!$I$12)/('Elicitation of functions'!$H$10-'Elicitation of functions'!$H$12)*(C27-'Elicitation of functions'!$H$12)+'Elicitation of functions'!$I$12,IF(C27<'Elicitation of functions'!$H$9,('Elicitation of functions'!$I$9-'Elicitation of functions'!$I$10)/('Elicitation of functions'!$H$9-'Elicitation of functions'!$H$10)*(C27-'Elicitation of functions'!$H$10)+'Elicitation of functions'!$I$10,IF(C27<'Elicitation of functions'!$H$11,('Elicitation of functions'!$I$11-'Elicitation of functions'!$I$9)/('Elicitation of functions'!$H$11-'Elicitation of functions'!$H$9)*(C27-'Elicitation of functions'!$H$9)+'Elicitation of functions'!$I$9,('Elicitation of functions'!$I$13-'Elicitation of functions'!$I$11)/('Elicitation of functions'!$H$13-'Elicitation of functions'!$H$11)*(C27-'Elicitation of functions'!$H$11)+'Elicitation of functions'!$I$11))) -> 0.4375 | N27: =IF(D27<'Elicitation of functions'!$H$20,('Elicitation of functions'!$I$20-'Elicitation of functions'!$I$22)/('Elicitation of functions'!$H$20-'Elicitation of functions'!$H$22)*(D27-'Elicitation of functions'!$H$22)+'Elicitation of functions'!$I$22,IF(D27<'Elicitation of functions'!$H$19,('Elicitation of functions'!$I$19-'Elicitation of functions'!$I$20)/('Elicitation of functions'!$H$19-'Elicitation of functions'!$H$20)*(D27-'Elicitation of functions'!$H$20)+'Elicitation of functions'!$I$20,IF(D27<'Elicitation of functions'!$H$21,('Elicitation of functions'!$I$21-'Elicitation of functions'!$I$19)/('Elicitation of functions'!$H$21-'Elicitation of functions'!$H$19)*(D27-'Elicitation of functions'!$H$19)+'Elicitation of functions'!$I$19,('Elicitation of functions'!$I$23-'Elicitation of functions'!$I$21)/('Elicitation of functions'!$H$23-'Elicitation of functions'!$H$21)*(D27-'Elicitation of functions'!$H$21)+'Elicitation of functions'!$I$21))) -> 0.42857143 | O27: =INDEX('Elicitation of functions'!$K$29:$K$33,MATCH(E27,'Elicitation of functions'!$F$29:$F$33,0)) -> 0.4 | P27: =INDEX('Elicitation of functions'!$K$39:$K$43,MATCH(F27,'Elicitation of functions'!$F$39:$F$43,0)) -> 0.3 | Q27: =INDEX('Elicitation of functions'!$K$49:$K$52,MATCH(G27,'Elicitation of functions'!$F$49:$F$52,0)) -> 1 | R27: =IF(H27<'Elicitation of functions'!$H$60,('Elicitation of functions'!$I$60-'Elicitation of functions'!$I$62)/('Elicitation of functions'!$H$60-'Elicitation of functions'!$H$62)*(H27-'Elicitation of functions'!$H$62)+'Elicitation of functions'!$I$62,IF(H27<'Elicitation of functions'!$H$59,('Elicitation of functions'!$I$59-'Elicitation of functions'!$I$60)/('Elicitation of functions'!$H$59-'Elicitation of functions'!$H$60)*(H27-'Elicitation of functions'!$H$60)+'Elicitation of functions'!$I$60,IF(H27<'Elicitation of functions'!$H$61,('Elicitation of functions'!$I$61-'Elicitation of functions'!$I$59)/('Elicitation of functions'!$H$61-'Elicitation of functions'!$H$59)*(H27-'Elicitation of functions'!$H$59)+'Elicitation of functions'!$I$59,('Elicitation of functions'!$I$63-'Elicitation of functions'!$I$61)/('Elicitation of functions'!$H$63-'Elicitation of functions'!$H$61)*(H27-'Elicitation of functions'!$H$61)+'Elicitation of functions'!$I$61))) -> 1 | S27: =IF(I27<'Elicitation of functions'!$H$70,('Elicitation of functions'!$I$70-'Elicitation of functions'!$I$72)/('Elicitation of functions'!$H$70-'Elicitation of functions'!$H$72)*(I27-'Elicitation of functions'!$H$72)+'Elicitation of functions'!$I$72,IF(I27<'Elicitation of functions'!$H$69,('Elicitation of functions'!$I$69-'Elicitation of functions'!$I$70)/('Elicitation of functions'!$H$69-'Elicitation of functions'!$H$70)*(I27-'Elicitation of functions'!$H$70)+'Elicitation of functions'!$I$70,IF(I27<'Elicitation of functions'!$H$71,('Elicitation of functions'!$I$71-'Elicitation of functions'!$I$69)/('Elicitation of functions'!$H$71-'Elicitation of functions'!$H$69)*(I27-'Elicitation of functions'!$H$69)+'Elicitation of functions'!$I$69,('Elicitation of functions'!$I$73-'Elicitation of functions'!$I$71)/('Elicitation of functions'!$H$73-'Elicitation of functions'!$H$71)*(I27-'Elicitation of functions'!$H$71)+'Elicitation of functions'!$I$71))) -> 0.45454545 | T27: =INDEX('Elicitation of functions'!$K$79:$K$83,MATCH(J27,'Elicitation of functions'!$F$79:$F$83,0)) -> 0.35 | V27: 0.3 | W27: 1 | X27: 1 | Y27: 0.454545 | Z27: 0.35
B28: Aalto-Certified Micro-Credentials | C28: 0.75 | D28: 0.7 | E28: Poor | F28: 2 | G28: Basic | H28: 0.55 | I28: 0.85 | J28: 2 | L28: =B28 -> Aalto-Certified Micro-Credentials | M28: =IF(C28<'Elicitation of functions'!$H$10,('Elicitation of functions'!$I$10-'Elicitation of functions'!$I$12)/('Elicitation of functions'!$H$10-'Elicitation of functions'!$H$12)*(C28-'Elicitation of functions'!$H$12)+'Elicitation of functions'!$I$12,IF(C28<'Elicitation of functions'!$H$9,('Elicitation of functions'!$I$9-'Elicitation of functions'!$I$10)/('Elicitation of functions'!$H$9-'Elicitation of functions'!$H$10)*(C28-'Elicitation of functions'!$H$10)+'Elicitation of functions'!$I$10,IF(C28<'Elicitation of functions'!$H$11,('Elicitation of functions'!$I$11-'Elicitation of functions'!$I$9)/('Elicitation of functions'!$H$11-'Elicitation of functions'!$H$9)*(C28-'Elicitation of functions'!$H$9)+'Elicitation of functions'!$I$9,('Elicitation of functions'!$I$13-'Elicitation of functions'!$I$11)/('Elicitation of functions'!$H$13-'Elicitation of functions'!$H$11)*(C28-'Elicitation of functions'!$H$11)+'Elicitation of functions'!$I$11))) -> 0.34375 | N28: =IF(D28<'Elicitation of functions'!$H$20,('Elicitation of functions'!$I$20-'Elicitation of functions'!$I$22)/('Elicitation of functions'!$H$20-'Elicitation of functions'!$H$22)*(D28-'Elicitation of functions'!$H$22)+'Elicitation of functions'!$I$22,IF(D28<'Elicitation of functions'!$H$19,('Elicitation of functions'!$I$19-'Elicitation of functions'!$I$20)/('Elicitation of functions'!$H$19-'Elicitation of functions'!$H$20)*(D28-'Elicitation of functions'!$H$20)+'Elicitation of functions'!$I$20,IF(D28<'Elicitation of functions'!$H$21,('Elicitation of functions'!$I$21-'Elicitation of functions'!$I$19)/('Elicitation of functions'!$H$21-'Elicitation of functions'!$H$19)*(D28-'Elicitation of functions'!$H$19)+'Elicitation of functions'!$I$19,('Elicitation of functions'!$I$23-'Elicitation of functions'!$I$21)/('Elicitation of functions'!$H$23-'Elicitation of functions'!$H$21)*(D28-'Elicitation of functions'!$H$21)+'Elicitation of functions'!$I$21))) -> 0.42857143 | O28: =INDEX('Elicitation of functions'!$K$29:$K$33,MATCH(E28,'Elicitation of functions'!$F$29:$F$33,0)) -> 0.2 | P28: =INDEX('Elicitation of functions'!$K$39:$K$43,MATCH(F28,'Elicitation of functions'!$F$39:$F$43,0)) -> 0.5 | Q28: =INDEX('Elicitation of functions'!$K$49:$K$52,MATCH(G28,'Elicitation of functions'!$F$49:$F$52,0)) -> 0.5 | R28: =IF(H28<'Elicitation of functions'!$H$60,('Elicitation of functions'!$I$60-'Elicitation of functions'!$I$62)/('Elicitation of functions'!$H$60-'Elicitation of functions'!$H$62)*(H28-'Elicitation of functions'!$H$62)+'Elicitation of functions'!$I$62,IF(H28<'Elicitation of functions'!$H$59,('Elicitation of functions'!$I$59-'Elicitation of functions'!$I$60)/('Elicitation of functions'!$H$59-'Elicitation of functions'!$H$60)*(H28-'Elicitation of functions'!$H$60)+'Elicitation of functions'!$I$60,IF(H28<'Elicitation of functions'!$H$61,('Elicitation of functions'!$I$61-'Elicitation of functions'!$I$59)/('Elicitation of functions'!$H$61-'Elicitation of functions'!$H$59)*(H28-'Elicitation of functions'!$H$59)+'Elicitation of functions'!$I$59,('Elicitation of functions'!$I$63-'Elicitation of functions'!$I$61)/('Elicitation of functions'!$H$63-'Elicitation of functions'!$H$61)*(H28-'Elicitation of functions'!$H$61)+'Elicitation of functions'!$I$61))) -> 0.58333333 | S28: =IF(I28<'Elicitation of functions'!$H$70,('Elicitation of functions'!$I$70-'Elicitation of functions'!$I$72)/('Elicitation of functions'!$H$70-'Elicitation of functions'!$H$72)*(I28-'Elicitation of functions'!$H$72)+'Elicitation of functions'!$I$72,IF(I28<'Elicitation of functions'!$H$69,('Elicitation of functions'!$I$69-'Elicitation of functions'!$I$70)/('Elicitation of functions'!$H$69-'Elicitation of functions'!$H$70)*(I28-'Elicitation of functions'!$H$70)+'Elicitation of functions'!$I$70,IF(I28<'Elicitation of functions'!$H$71,('Elicitation of functions'!$I$71-'Elicitation of functions'!$I$69)/('Elicitation of functions'!$H$71-'Elicitation of functions'!$H$69)*(I28-'Elicitation of functions'!$H$69)+'Elicitation of functions'!$I$69,('Elicitation of functions'!$I$73-'Elicitation of functions'!$I$71)/('Elicitation of functions'!$H$73-'Elicitation of functions'!$H$71)*(I28-'Elicitation of functions'!$H$71)+'Elicitation of functions'!$I$71))) -> 0.59375 | T28: =INDEX('Elicitation of functions'!$K$79:$K$83,MATCH(J28,'Elicitation of functions'!$F$79:$F$83,0)) -> 0.2 | V28: 0.5 | W28: 0.5 | X28: 0.583333 | Y28: 0.59375 | Z28: 0.2
B29: Pedagogical Training for Staff | C29: 0.82 | D29: 0.75 | E29: Acceptable | F29: 1 | G29: Robust | H29: 0.55 | I29: 0.82 | J29: 3 | L29: =B29 -> Pedagogical Training for Staff | M29: =IF(C29<'Elicitation of functions'!$H$10,('Elicitation of functions'!$I$10-'Elicitation of functions'!$I$12)/('Elicitation of functions'!$H$10-'Elicitation of functions'!$H$12)*(C29-'Elicitation of functions'!$H$12)+'Elicitation of functions'!$I$12,IF(C29<'Elicitation of functions'!$H$9,('Elicitation of functions'!$I$9-'Elicitation of functions'!$I$10)/('Elicitation of functions'!$H$9-'Elicitation of functions'!$H$10)*(C29-'Elicitation of functions'!$H$10)+'Elicitation of functions'!$I$10,IF(C29<'Elicitation of functions'!$H$11,('Elicitation of functions'!$I$11-'Elicitation of functions'!$I$9)/('Elicitation of functions'!$H$11-'Elicitation of functions'!$H$9)*(C29-'Elicitation of functions'!$H$9)+'Elicitation of functions'!$I$9,('Elicitation of functions'!$I$13-'Elicitation of functions'!$I$11)/('Elicitation of functions'!$H$13-'Elicitation of functions'!$H$11)*(C29-'Elicitation of functions'!$H$11)+'Elicitation of functions'!$I$11))) -> 0.6 | N29: =IF(D29<'Elicitation of functions'!$H$20,('Elicitation of functions'!$I$20-'Elicitation of functions'!$I$22)/('Elicitation of functions'!$H$20-'Elicitation of functions'!$H$22)*(D29-'Elicitation of functions'!$H$22)+'Elicitation of functions'!$I$22,IF(D29<'Elicitation of functions'!$H$19,('Elicitation of functions'!$I$19-'Elicitation of functions'!$I$20)/('Elicitation of functions'!$H$19-'Elicitation of functions'!$H$20)*(D29-'Elicitation of functions'!$H$20)+'Elicitation of functions'!$I$20,IF(D29<'Elicitation of functions'!$H$21,('Elicitation of functions'!$I$21-'Elicitation of functions'!$I$19)/('Elicitation of functions'!$H$21-'Elicitation of functions'!$H$19)*(D29-'Elicitation of functions'!$H$19)+'Elicitation of functions'!$I$19,('Elicitation of functions'!$I$23-'Elicitation of functions'!$I$21)/('Elicitation of functions'!$H$23-'Elicitation of functions'!$H$21)*(D29-'Elicitation of functions'!$H$21)+'Elicitation of functions'!$I$21))) -> 0.59375 | O29: =INDEX('Elicitation of functions'!$K$29:$K$33,MATCH(E29,'Elicitation of functions'!$F$29:$F$33,0)) -> 0.4 | P29: =INDEX('Elicitation of functions'!$K$39:$K$43,MATCH(F29,'Elicitation of functions'!$F$39:$F$43,0)) -> 0.3 | Q29: =INDEX('Elicitation of functions'!$K$49:$K$52,MATCH(G29,'Elicitation of functions'!$F$49:$F$52,0)) -> 0.75 | R29: =IF(H29<'Elicitation of functions'!$H$60,('Elicitation of functions'!$I$60-'Elicitation of functions'!$I$62)/('Elicitation of functions'!$H$60-'Elicitation of functions'!$H$62)*(H29-'Elicitation of functions'!$H$62)+'Elicitation of functions'!$I$62,IF(H29<'Elicitation of functions'!$H$59,('Elicitation of functions'!$I$59-'Elicitation of functions'!$I$60)/('Elicitation of functions'!$H$59-'Elicitation of functions'!$H$60)*(H29-'Elicitation of functions'!$H$60)+'Elicitation of functions'!$I$60,IF(H29<'Elicitation of functions'!$H$61,('Elicitation of functions'!$I$61-'Elicitation of functions'!$I$59)/('Elicitation of functions'!$H$61-'Elicitation of functions'!$H$59)*(H29-'Elicitation of functions'!$H$59)+'Elicitation of functions'!$I$59,('Elicitation of functions'!$I$63-'Elicitation of functions'!$I$61)/('Elicitation of functions'!$H$63-'Elicitation of functions'!$H$61)*(H29-'Elicitation of functions'!$H$61)+'Elicitation of functions'!$I$61))) -> 0.58333333 | S29: =IF(I29<'Elicitation of functions'!$H$70,('Elicitation of functions'!$I$70-'Elicitation of functions'!$I$72)/('Elicitation of functions'!$H$70-'Elicitation of functions'!$H$72)*(I29-'Elicitation of functions'!$H$72)+'Elicitation of functions'!$I$72,IF(I29<'Elicitation of functions'!$H$69,('Elicitation of functions'!$I$69-'Elicitation of functions'!$I$70)/('Elicitation of functions'!$H$69-'Elicitation of functions'!$H$70)*(I29-'Elicitation of functions'!$H$70)+'Elicitation of functions'!$I$70,IF(I29<'Elicitation of functions'!$H$71,('Elicitation of functions'!$I$71-'Elicitation of functions'!$I$69)/('Elicitation of functions'!$H$71-'Elicitation of functions'!$H$69)*(I29-'Elicitation of functions'!$H$69)+'Elicitation of functions'!$I$69,('Elicitation of functions'!$I$73-'Elicitation of functions'!$I$71)/('Elicitation of functions'!$H$73-'Elicitation of functions'!$H$71)*(I29-'Elicitation of functions'!$H$71)+'Elicitation of functions'!$I$71))) -> 0.5 | T29: =INDEX('Elicitation of functions'!$K$79:$K$83,MATCH(J29,'Elicitation of functions'!$F$79:$F$83,0)) -> 0.35 | V29: 0.3 | W29: 0.75 | X29: 0.583333 | Y29: 0.5 | Z29: 0.35
B30: Nordic-Baltic Tech Alliance | C30: 0.85 | D30: 0.78 | E30: Good | F30: 1 | G30: Exemplary | H30: 0.85 | I30: 0.92 | J30: 5 | L30: =B30 -> Nordic-Baltic Tech Alliance | M30: =IF(C30<'Elicitation of functions'!$H$10,('Elicitation of functions'!$I$10-'Elicitation of functions'!$I$12)/('Elicitation of functions'!$H$10-'Elicitation of functions'!$H$12)*(C30-'Elicitation of functions'!$H$12)+'Elicitation of functions'!$I$12,IF(C30<'Elicitation of functions'!$H$9,('Elicitation of functions'!$I$9-'Elicitation of functions'!$I$10)/('Elicitation of functions'!$H$9-'Elicitation of functions'!$H$10)*(C30-'Elicitation of functions'!$H$10)+'Elicitation of functions'!$I$10,IF(C30<'Elicitation of functions'!$H$11,('Elicitation of functions'!$I$11-'Elicitation of functions'!$I$9)/('Elicitation of functions'!$H$11-'Elicitation of functions'!$H$9)*(C30-'Elicitation of functions'!$H$9)+'Elicitation of functions'!$I$9,('Elicitation of functions'!$I$13-'Elicitation of functions'!$I$11)/('Elicitation of functions'!$H$13-'Elicitation of functions'!$H$11)*(C30-'Elicitation of functions'!$H$11)+'Elicitation of functions'!$I$11))) -> 0.75 | N30: =IF(D30<'Elicitation of functions'!$H$20,('Elicitation of functions'!$I$20-'Elicitation of functions'!$I$22)/('Elicitation of functions'!$H$20-'Elicitation of functions'!$H$22)*(D30-'Elicitation of functions'!$H$22)+'Elicitation of functions'!$I$22,IF(D30<'Elicitation of functions'!$H$19,('Elicitation of functions'!$I$19-'Elicitation of functions'!$I$20)/('Elicitation of functions'!$H$19-'Elicitation of functions'!$H$20)*(D30-'Elicitation of functions'!$H$20)+'Elicitation of functions'!$I$20,IF(D30<'Elicitation of functions'!$H$21,('Elicitation of functions'!$I$21-'Elicitation of functions'!$I$19)/('Elicitation of functions'!$H$21-'Elicitation of functions'!$H$19)*(D30-'Elicitation of functions'!$H$19)+'Elicitation of functions'!$I$19,('Elicitation of functions'!$I$23-'Elicitation of functions'!$I$21)/('Elicitation of functions'!$H$23-'Elicitation of functions'!$H$21)*(D30-'Elicitation of functions'!$H$21)+'Elicitation of functions'!$I$21))) -> 0.6875 | O30: =INDEX('Elicitation of functions'!$K$29:$K$33,MATCH(E30,'Elicitation of functions'!$F$29:$F$33,0)) -> 0.7 | P30: =INDEX('Elicitation of functions'!$K$39:$K$43,MATCH(F30,'Elicitation of functions'!$F$39:$F$43,0)) -> 0.3 | Q30: =INDEX('Elicitation of functions'!$K$49:$K$52,MATCH(G30,'Elicitation of functions'!$F$49:$F$52,0)) -> 1 | R30: =IF(H30<'Elicitation of functions'!$H$60,('Elicitation of functions'!$I$60-'Elicitation of functions'!$I$62)/('Elicitation of functions'!$H$60-'Elicitation of functions'!$H$62)*(H30-'Elicitation of functions'!$H$62)+'Elicitation of functions'!$I$62,IF(H30<'Elicitation of functions'!$H$59,('Elicitation of functions'!$I$59-'Elicitation of functions'!$I$60)/('Elicitation of functions'!$H$59-'Elicitation of functions'!$H$60)*(H30-'Elicitation of functions'!$H$60)+'Elicitation of functions'!$I$60,IF(H30<'Elicitation of functions'!$H$61,('Elicitation of functions'!$I$61-'Elicitation of functions'!$I$59)/('Elicitation of functions'!$H$61-'Elicitation of functions'!$H$59)*(H30-'Elicitation of functions'!$H$59)+'Elicitation of functions'!$I$59,('Elicitation of functions'!$I$63-'Elicitation of functions'!$I$61)/('Elicitation of functions'!$H$63-'Elicitation of functions'!$H$61)*(H30-'Elicitation of functions'!$H$61)+'Elicitation of functions'!$I$61))) -> 0.91666667 | S30: =IF(I30<'Elicitation of functions'!$H$70,('Elicitation of functions'!$I$70-'Elicitation of functions'!$I$72)/('Elicitation of functions'!$H$70-'Elicitation of functions'!$H$72)*(I30-'Elicitation of functions'!$H$72)+'Elicitation of functions'!$I$72,IF(I30<'Elicitation of functions'!$H$69,('Elicitation of functions'!$I$69-'Elicitation of functions'!$I$70)/('Elicitation of functions'!$H$69-'Elicitation of functions'!$H$70)*(I30-'Elicitation of functions'!$H$70)+'Elicitation of functions'!$I$70,IF(I30<'Elicitation of functions'!$H$71,('Elicitation of functions'!$I$71-'Elicitation of functions'!$I$69)/('Elicitation of functions'!$H$71-'Elicitation of functions'!$H$69)*(I30-'Elicitation of functions'!$H$69)+'Elicitation of functions'!$I$69,('Elicitation of functions'!$I$73-'Elicitation of functions'!$I$71)/('Elicitation of functions'!$H$73-'Elicitation of functions'!$H$71)*(I30-'Elicitation of functions'!$H$71)+'Elicitation of functions'!$I$71))) -> 0.85 | T30: =INDEX('Elicitation of functions'!$K$79:$K$83,MATCH(J30,'Elicitation of functions'!$F$79:$F$83,0)) -> 1 | V30: 0.3 | W30: 1 | X30: 0.916667 | Y30: 0.85 | Z30: 1

Sheet Portfolio model
F2: Competitive Global Campus | N2: Always-Learning Society | V2: Human-First University | AF2: Actions' scenario-specific utilities
F3: Achievement of learning outcomes (65-95%) | G3: Completion and progression (55-90%) | H3: Learner experience and engagement | I3: Accessibility, flexibility and equity (0-4) | J3: Integrity of assessment | K3: Strategic control / autonomy (20-90%) | L3: External relevance and employability (65-95%) | M3: Global attractiveness / reputation (1-5) | N3: Achievement of learning outcomes (65-95%) | O3: Completion and progression (55-90%) | P3: Learner experience and engagement | Q3: Accessibility, flexibility and equity (0-4) | R3: Integrity of assessment | S3: Strategic control / autonomy (20-90%) | T3: External relevance and employability (65-95%) | U3: Global attractiveness / reputation (1-5) | V3: Achievement of learning outcomes (65-95%) | W3: Completion and progression (55-90%) | X3: Learner experience and engagement | Y3: Accessibility, flexibility and equity (0-4) | Z3: Integrity of assessment | AA3: Strategic control / autonomy (20-90%) | AB3: External relevance and employability (65-95%) | AC3: Global attractiveness / reputation (1-5) | AF3: p1 | AG3: p2 | AH3: p3
F4: ='Action Performance by Scenario'!M6 -> 0.6 | G4: ='Action Performance by Scenario'!N6 -> 0.6875 | H4: ='Action Performance by Scenario'!O6 -> 0.7 | I4: ='Action Performance by Scenario'!P6 -> 0.8 | J4: ='Action Performance by Scenario'!Q6 -> 0.5 | K4: ='Action Performance by Scenario'!R6 -> 0.41666667 | L4: ='Action Performance by Scenario'!S6 -> 0.5 | M4: ='Action Performance by Scenario'!T6 -> 0.35 | N4: ='Action Performance by Scenario'!M15 -> 0.825 | O4: ='Action Performance by Scenario'!N15 -> 0.875 | P4: ='Action Performance by Scenario'!O15 -> 0.4 | Q4: ='Action Performance by Scenario'!P15 -> 1 | R4: ='Action Performance by Scenario'!Q15 -> 0 | S4: ='Action Performance by Scenario'!R15 -> 0.33333333 | T4: ='Action Performance by Scenario'!S15 -> 0.59375 | U4: ='Action Performance by Scenario'!T15 -> 0.35 | V4: ='Action Performance by Scenario'!M24 -> 0.5 | W4: ='Action Performance by Scenario'!N24 -> 0.59375 | X4: ='Action Performance by Scenario'!O24 -> 0 | Y4: ='Action Performance by Scenario'!P24 -> 0.5 | Z4: ='Action Performance by Scenario'!Q24 -> 0 | AA4: ='Action Performance by Scenario'!R24 -> 0.5 | AB4: ='Action Performance by Scenario'!S24 -> 0.45454545 | AC4: ='Action Performance by Scenario'!T24 -> 0.2 | AF4: {=SUMPRODUCT(F4:M4, TRANSPOSE($B$14:$B$21))} -> 0.55299045 | AG4: {=SUMPRODUCT(G4:N4, TRANSPOSE($B$14:$B$21))} -> 0.58820126 | AH4: {=SUMPRODUCT(H4:O4, TRANSPOSE($B$14:$B$21))} -> 0.73684524 | AJ4: {=SUMPRODUCT(AF4:AH4, TRANSPOSE($B$24:$B$26))} -> 0.62557894
F5: ='Action Performance by Scenario'!M7 -> 0.75 | G5: ='Action Performance by Scenario'!N7 -> 0.59375 | H5: ='Action Performance by Scenario'!O7 -> 1 | I5: ='Action Performance by Scenario'!P7 -> 0.3 | J5: ='Action Performance by Scenario'!Q7 -> 0.75 | K5: ='Action Performance by Scenario'!R7 -> 0.5 | L5: ='Action Performance by Scenario'!S7 -> 0.75 | M5: ='Action Performance by Scenario'!T7 -> 0.7 | N5: ='Action Performance by Scenario'!M16 -> 0.6 | O5: ='Action Performance by Scenario'!N16 -> 0.75 | P5: ='Action Performance by Scenario'!O16 -> 1 | Q5: ='Action Performance by Scenario'!P16 -> 0.3 | R5: ='Action Performance by Scenario'!Q16 -> 0.75 | S5: ='Action Performance by Scenario'!R16 -> 0.41666667 | T5: ='Action Performance by Scenario'!S16 -> 1 | U5: ='Action Performance by Scenario'!T16 -> 0.7 | V5: ='Action Performance by Scenario'!M25 -> 0.5 | W5: ='Action Performance by Scenario'!N25 -> 0.5 | X5: ='Action Performance by Scenario'!O25 -> 0.7 | Y5: ='Action Performance by Scenario'!P25 -> 0 | Z5: ='Action Performance by Scenario'!Q25 -> 0.75 | AA5: ='Action Performance by Scenario'!R25 -> 0.54166667 | AB5: ='Action Performance by Scenario'!S25 -> 0.6875 | AC5: ='Action Performance by Scenario'!T25 -> 0.35 | AF5: {=SUMPRODUCT(F5:M5, TRANSPOSE($B$14:$B$21))} -> 0.70783203 | AG5: {=SUMPRODUCT(G5:N5, TRANSPOSE($B$14:$B$21))} -> 0.69780785 | AH5: {=SUMPRODUCT(H5:O5, TRANSPOSE($B$14:$B$21))} -> 0.61115327 | AJ5: {=SUMPRODUCT(AF5:AH5, TRANSPOSE($B$24:$B$26))} -> 0.67485093
F6: ='Action Performance by Scenario'!M8 -> 0.34375 | G6: ='Action Performance by Scenario'!N8 -> 0.25 | H6: ='Action Performance by Scenario'!O8 -> 0.2 | I6: ='Action Performance by Scenario'!P8 -> 0.5 | J6: ='Action Performance by Scenario'!Q8 -> 1 | K6: ='Action Performance by Scenario'!R8 -> 0.625 | L6: ='Action Performance by Scenario'!S8 -> 0.45454545 | M6: ='Action Performance by Scenario'!T8 -> 0.35 | N6: ='Action Performance by Scenario'!M17 -> 0.4375 | O6: ='Action Performance by Scenario'!N17 -> 0.35714286 | P6: ='Action Performance by Scenario'!O17 -> 0.2 | Q6: ='Action Performance by Scenario'!P17 -> 0.5 | R6: ='Action Performance by Scenario'!Q17 -> 1 | S6: ='Action Performance by Scenario'!R17 -> 0.58333333 | T6: ='Action Performance by Scenario'!S17 -> 0.5 | U6: ='Action Performance by Scenario'!T17 -> 0.7 | V6: ='Action Performance by Scenario'!M26 -> 0.34375 | W6: ='Action Performance by Scenario'!N26 -> 0.25 | X6: ='Action Performance by Scenario'!O26 -> 0.4 | Y6: ='Action Performance by Scenario'!P26 -> 0.3 | Z6: ='Action Performance by Scenario'!Q26 -> 1 | AA6: ='Action Performance by Scenario'!R26 -> 0.75 | AB6: ='Action Performance by Scenario'!S26 -> 0.40909091 | AC6: ='Action Performance by Scenario'!T26 -> 0.7 | AF6: {=SUMPRODUCT(F6:M6, TRANSPOSE($B$14:$B$21))} -> 0.37707902 | AG6: {=SUMPRODUCT(G6:N6, TRANSPOSE($B$14:$B$21))} -> 0.37150247 | AH6: {=SUMPRODUCT(H6:O6, TRANSPOSE($B$14:$B$21))} -> 0.48383511 | AJ6: {=SUMPRODUCT(AF6:AH6, TRANSPOSE($B$24:$B$26))} -> 0.4033256
F7: ='Action Performance by Scenario'!M9 -> 0.5 | G7: ='Action Performance by Scenario'!N9 -> 0.5 | H7: ='Action Performance by Scenario'!O9 -> 0.4 | I7: ='Action Performance by Scenario'!P9 -> 0.5 | J7: ='Action Performance by Scenario'!Q9 -> 0.75 | K7: ='Action Performance by Scenario'!R9 -> 0.83333333 | L7: ='Action Performance by Scenario'!S9 -> 0.5 | M7: ='Action Performance by Scenario'!T9 -> 0.2 | N7: ='Action Performance by Scenario'!M18 -> 0.6 | O7: ='Action Performance by Scenario'!N18 -> 0.59375 | P7: ='Action Performance by Scenario'!O18 -> 0.2 | Q7: ='Action Performance by Scenario'!P18 -> 0.8 | R7: ='Action Performance by Scenario'!Q18 -> 0.75 | S7: ='Action Performance by Scenario'!R18 -> 0.91666667 | T7: ='Action Performance by Scenario'!S18 -> 0.59375 | U7: ='Action Performance by Scenario'!T18 -> 0.2 | V7: ='Action Performance by Scenario'!M27 -> 0.4375 | W7: ='Action Performance by Scenario'!N27 -> 0.42857143 | X7: ='Action Performance by Scenario'!O27 -> 0.4 | Y7: ='Action Performance by Scenario'!P27 -> 0.3 | Z7: ='Action Performance by Scenario'!Q27 -> 1 | AA7: ='Action Performance by Scenario'!R27 -> 1 | AB7: ='Action Performance by Scenario'!S27 -> 0.45454545 | AC7: ='Action Performance by Scenario'!T27 -> 0.35 | AF7: {=SUMPRODUCT(F7:M7, TRANSPOSE($B$14:$B$21))} -> 0.46528522 | AG7: {=SUMPRODUCT(G7:N7, TRANSPOSE($B$14:$B$21))} -> 0.40540923 | AH7: {=SUMPRODUCT(H7:O7, TRANSPOSE($B$14:$B$21))} -> 0.56282087 | AJ7: {=SUMPRODUCT(AF7:AH7, TRANSPOSE($B$24:$B$26))} -> 0.45578757
F8: ='Action Performance by Scenario'!M10 -> 0.5 | G8: ='Action Performance by Scenario'!N10 -> 0.59375 | H8: ='Action Performance by Scenario'!O10 -> 0.7 | I8: ='Action Performance by Scenario'!P10 -> 1 | J8: ='Action Performance by Scenario'!Q10 -> 0.5 | K8: ='Action Performance by Scenario'!R10 -> 0.54166667 | L8: ='Action Performance by Scenario'!S10 -> 0.6875 | M8: ='Action Performance by Scenario'!T10 -> 0.7 | N8: ='Action Performance by Scenario'!M19 -> 0.75 | O8: ='Action Performance by Scenario'!N19 -> 0.8 | P8: ='Action Performance by Scenario'!O19 -> 0.7 | Q8: ='Action Performance by Scenario'!P19 -> 1 | R8: ='Action Performance by Scenario'!Q19 -> 0.5 | S8: ='Action Performance by Scenario'!R19 -> 0.5 | T8: ='Action Performance by Scenario'!S19 -> 0.85 | U8: ='Action Performance by Scenario'!T19 -> 0.7 | V8: ='Action Performance by Scenario'!M28 -> 0.34375 | W8: ='Action Performance by Scenario'!N28 -> 0.42857143 | X8: ='Action Performance by Scenario'!O28 -> 0.2 | Y8: ='Action Performance by Scenario'!P28 -> 0.5 | Z8: ='Action Performance by Scenario'!Q28 -> 0.5 | AA8: ='Action Performance by Scenario'!R28 -> 0.58333333 | AB8: ='Action Performance by Scenario'!S28 -> 0.59375 | AC8: ='Action Performance by Scenario'!T28 -> 0.2 | AF8: {=SUMPRODUCT(F8:M8, TRANSPOSE($B$14:$B$21))} -> 0.65539466 | AG8: {=SUMPRODUCT(G8:N8, TRANSPOSE($B$14:$B$21))} -> 0.72250465 | AH8: {=SUMPRODUCT(H8:O8, TRANSPOSE($B$14:$B$21))} -> 0.76901972 | AJ8: {=SUMPRODUCT(AF8:AH8, TRANSPOSE($B$24:$B$26))} -> 0.72796884
F9: ='Action Performance by Scenario'!M11 -> 0.75 | G9: ='Action Performance by Scenario'!N11 -> 0.6875 | H9: ='Action Performance by Scenario'!O11 -> 0.7 | I9: ='Action Performance by Scenario'!P11 -> 0.5 | J9: ='Action Performance by Scenario'!Q11 -> 0.75 | K9: ='Action Performance by Scenario'!R11 -> 0.54166667 | L9: ='Action Performance by Scenario'!S11 -> 0.5625 | M9: ='Action Performance by Scenario'!T11 -> 0.35 | N9: ='Action Performance by Scenario'!M20 -> 0.825 | O9: ='Action Performance by Scenario'!N20 -> 0.75 | P9: ='Action Performance by Scenario'!O20 -> 0.7 | Q9: ='Action Performance by Scenario'!P20 -> 0.8 | R9: ='Action Performance by Scenario'!Q20 -> 0.75 | S9: ='Action Performance by Scenario'!R20 -> 0.5 | T9: ='Action Performance by Scenario'!S20 -> 0.59375 | U9: ='Action Performance by Scenario'!T20 -> 0.35 | V9: ='Action Performance by Scenario'!M29 -> 0.6 | W9: ='Action Performance by Scenario'!N29 -> 0.59375 | X9: ='Action Performance by Scenario'!O29 -> 0.4 | Y9: ='Action Performance by Scenario'!P29 -> 0.3 | Z9: ='Action Performance by Scenario'!Q29 -> 0.75 | AA9: ='Action Performance by Scenario'!R29 -> 0.58333333 | AB9: ='Action Performance by Scenario'!S29 -> 0.5 | AC9: ='Action Performance by Scenario'!T29 -> 0.35 | AF9: {=SUMPRODUCT(F9:M9, TRANSPOSE($B$14:$B$21))} -> 0.58677207 | AG9: {=SUMPRODUCT(G9:N9, TRANSPOSE($B$14:$B$21))} -> 0.56875 | AH9: {=SUMPRODUCT(H9:O9, TRANSPOSE($B$14:$B$21))} -> 0.68619978 | AJ9: {=SUMPRODUCT(AF9:AH9, TRANSPOSE($B$24:$B$26))} -> 0.60337739
F10: ='Action Performance by Scenario'!M12 -> 0.6 | G10: ='Action Performance by Scenario'!N12 -> 0.59375 | H10: ='Action Performance by Scenario'!O12 -> 0.4 | I10: ='Action Performance by Scenario'!P12 -> 0.3 | J10: ='Action Performance by Scenario'!Q12 -> 0.75 | K10: ='Action Performance by Scenario'!R12 -> 0.66666667 | L10: ='Action Performance by Scenario'!S12 -> 0.625 | M10: ='Action Performance by Scenario'!T12 -> 0.7 | N10: ='Action Performance by Scenario'!M21 -> 0.5 | O10: ='Action Performance by Scenario'!N21 -> 0.5 | P10: ='Action Performance by Scenario'!O21 -> 0.4 | Q10: ='Action Performance by Scenario'!P21 -> 0.5 | R10: ='Action Performance by Scenario'!Q21 -> 0.75 | S10: ='Action Performance by Scenario'!R21 -> 0.58333333 | T10: ='Action Performance by Scenario'!S21 -> 0.6875 | U10: ='Action Performance by Scenario'!T21 -> 0.35 | V10: ='Action Performance by Scenario'!M30 -> 0.75 | W10: ='Action Performance by Scenario'!N30 -> 0.6875 | X10: ='Action Performance by Scenario'!O30 -> 0.7 | Y10: ='Action Performance by Scenario'!P30 -> 0.3 | Z10: ='Action Performance by Scenario'!Q30 -> 1 | AA10: ='Action Performance by Scenario'!R30 -> 0.91666667 | AB10: ='Action Performance by Scenario'!S30 -> 0.85 | AC10: ='Action Performance by Scenario'!T30 -> 1 | AF10: {=SUMPRODUCT(F10:M10, TRANSPOSE($B$14:$B$21))} -> 0.59618149 | AG10: {=SUMPRODUCT(G10:N10, TRANSPOSE($B$14:$B$21))} -> 0.54956008 | AH10: {=SUMPRODUCT(H10:O10, TRANSPOSE($B$14:$B$21))} -> 0.49515997 | AJ10: {=SUMPRODUCT(AF10:AH10, TRANSPOSE($B$24:$B$26))} -> 0.5396291
A13: Attribute weights
A14: Achievement of learning outcomes | B14: 0.079315476
A15: Completion and progression | B15: 0.21473214
A16: Learner experience and engagement | B16: 0.11056548
A17: Accessibility flexibility and equity | B17: 0.033482143
A18: Integrity of assessment | B18: 0.015625
A19: Strategic control / autonomy | B19: 0.054315476
A20: External relevance and employability | B20: 0.33973214
A21: Global attractiveness / reputation | B21: 0.15223214
A23: Scenario Probabilities
A24: Competitive Global Campus | B24: 0.11111111
A25: Always-Learning Society | B25: 0.61111111
A26: Human-First University | B26: 0.27777778
A28: Action Proposals | B28: Decision variables | C28: Cost (M€) | D28: Time (years) | E28: Implementation capacity points | F28: Category
A29: AI-Enabled Student Guidance | B29: 0 | C29: 1.2 | D29: 1.5 | E29: 2 | F29: Student Support & AI
A30: Elite Mentor Network / Smart Work-Study | B30: 1 | C30: 1 | D30: 1 | E30: 1 | F30: Work-Integrated Learning
A31: AI Governance Board / Assessment Integrity | B31: 0 | C31: 0.5 | D31: 0.8 | E31: 1 | F31: Governance & Integrity
A32: Aalto-Controlled Core Infrastructure | B32: 1 | C32: 2 | D32: 2 | E32: 2 | F32: Digital Infrastructure
A33: Aalto-Certified Micro-Credentials | B33: 1 | C33: 1.1 | D33: 1.2 | E33: 1 | F33: Flexible Learning Pathways
A34: Pedagogical Training for Staff | B34: 1 | C34: 0.8 | D34: 1 | E34: 2 | F34: Faculty Capability
A35: Nordic-Baltic Tech Alliance | B35: 0 | C35: 1.4 | D35: 1.5 | E35: 1 | F35: Partnerships & Reputation
A36: Expected portfolio utility | B36: =SUMPRODUCT(AJ4:AJ10,B29:B35) -> 2.4619847
A39: Constraint type | B39: Expression | D39: Limit
A40: Budget | B40: =SUMPRODUCT(C29:C35,B29:B35) -> 4.9 | C40: <= | D40: 5
A41: Implementation capacity | B41: =SUMPRODUCT(E29:E35,B29:B35) -> 6 | C41: <= | D41: 6
A42: Number of actions | B42: =SUM(B29:B35) -> 4 | C42: <= | D42: 4
A43: Dependency | B43: =B33-B32 -> 0 | C43: <= | D43: 0
A44: Balance | B44: =B30+B33+B35 -> 2 | C44: >= | D44: 1
A45: Time | B45: =SUMPRODUCT(B29:B35,D29:D35) -> 5.2 | C45: <= | D45: 10

Sheet Sensitivity analysis
A1: Sensitivity Analysis
A2: Use this sheet as the rerun log: the Base case row now links directly to the current Portfolio model output. For the other cases, update the case inputs, rerun Solver on Portfolio model, then paste the resulting utility and selected-action text here. | W2: Blue/green status cells are formula-driven.
A4: Case | B4: p1: CGC | C4: p2: ALS | D4: p3: HFU | E4: Budget (M€) | F4: Capacity | G4: Max actions | H4: Time limit | I4: Optimal utility | J4: Selected actions | K4: Budget used | L4: Capacity used | M4: Time used | N4: Portfolio changed? | O4: AI-Enabled Student Guidance | P4: Elite Mentor Network / Smart Work-Study | Q4: AI Governance Board / Assessment Integrity | R4: Aalto-Controlled Core Infrastructure | S4: Aalto-Certified Micro-Credentials | T4: Pedagogical Training for Staff | U4: Nordic-Baltic Tech Alliance | V4: Comment | W4: Utility delta vs base | X4: How to rerun
A5: Base case | B5: ='Portfolio model'!$B$24 -> 0.11111111 | C5: ='Portfolio model'!$B$25 -> 0.61111111 | D5: ='Portfolio model'!$B$26 -> 0.27777778 | E5: ='Portfolio model'!$D$40 -> 5 | F5: ='Portfolio model'!$D$41 -> 6 | G5: ='Portfolio model'!$D$42 -> 4 | H5: ='Portfolio model'!$D$45 -> 10 | I5: ='Portfolio model'!$B$36 -> 2.4619847 | J5: =TRIM(MID(IF('Portfolio model'!$B$29=1,", "&'Portfolio model'!$A$29,"")&IF('Portfolio model'!$B$30=1,", "&'Portfolio model'!$A$30,"")&IF('Portfolio model'!$B$31=1,", "&'Portfolio model'!$A$31,"")&IF('Portfolio model'!$B$32=1,", "&'Portfolio model'!$A$32,"")&IF('Portfolio model'!$B$33=1,", "&'Portfolio model'!$A$33,"")&IF('Portfolio model'!$B$34=1,", "&'Portfolio model'!$A$34,"")&IF('Portfolio model'!$B$35=1,", "&'Portfolio model'!$A$35,""),3,999)) -> Elite Mentor Network / Smart Work-Study, Aalto-Controlled Core Infrastructure, Aalto-Certified Micro-Credentials, Pedagogical Training for Staff | K5: ='Portfolio model'!$B$40 -> 4.9 | L5: ='Portfolio model'!$B$41 -> 6 | M5: ='Portfolio model'!$B$45 -> 5.2 | N5: Base | O5: ='Portfolio model'!$B$29 -> 0 | P5: ='Portfolio model'!$B$30 -> 1 | Q5: ='Portfolio model'!$B$31 -> 0 | R5: ='Portfolio model'!$B$32 -> 1 | S5: ='Portfolio model'!$B$33 -> 1 | T5: ='Portfolio model'!$B$34 -> 1 | U5: ='Portfolio model'!$B$35 -> 0 | V5: Original model inputs | W5: =IFERROR(I5-$I$5,"") -> 0 | X5: 1) Change probabilities / limits on Portfolio model
A6: Equal probabilities | B6: 0.33333333 | C6: 0.33333333 | D6: 0.33333333 | E6: 5 | F6: 6 | G6: 4 | H6: 10 | I6: 2.4888331 | J6: Elite Mentor Network / Smart Work-Study, Aalto-Controlled Core Infrastructure, Aalto-Certified Micro-Credentials, Pedagogical Training for Staff | K6: 4.9 | L6: 6 | M6: 5.2 | N6: =IF(SUMPRODUCT(--(O6:U6=$O$5:$U$5))=7,"No","Yes") -> No | O6: =--ISNUMBER(SEARCH(O$4,$J6)) -> 0 | P6: =--ISNUMBER(SEARCH(P$4,$J6)) -> 1 | Q6: =--ISNUMBER(SEARCH(Q$4,$J6)) -> 0 | R6: =--ISNUMBER(SEARCH(R$4,$J6)) -> 1 | S6: =--ISNUMBER(SEARCH(S$4,$J6)) -> 1 | T6: =--ISNUMBER(SEARCH(T$4,$J6)) -> 1 | U6: =--ISNUMBER(SEARCH(U$4,$J6)) -> 0 | V6: Tests scenario-probability ambiguity | W6: =IFERROR(I6-$I$5,"") -> 0.026848384 | X6: 2) Run Data > Solver
A7: Scenario 1 favored | B7: 0.5 | C7: 0.25 | D7: 0.25 | E7: 5 | F7: 6 | G7: 4 | H7: 10 | I7: 2.4704458 | J7: Elite Mentor Network / Smart Work-Study, Aalto-Controlled Core Infrastructure, Aalto-Certified Micro-Credentials, Pedagogical Training for Staff | K7: 4.9 | L7: 6 | M7: 5.2 | N7: =IF(SUMPRODUCT(--(O7:U7=$O$5:$U$5))=7,"No","Yes") -> No | O7: =--ISNUMBER(SEARCH(O$4,$J7)) -> 0 | P7: =--ISNUMBER(SEARCH(P$4,$J7)) -> 1 | Q7: =--ISNUMBER(SEARCH(Q$4,$J7)) -> 0 | R7: =--ISNUMBER(SEARCH(R$4,$J7)) -> 1 | S7: =--ISNUMBER(SEARCH(S$4,$J7)) -> 1 | T7: =--ISNUMBER(SEARCH(T$4,$J7)) -> 1 | U7: =--ISNUMBER(SEARCH(U$4,$J7)) -> 0 | V7: Tests stronger competitive-global-campus view | W7: =IFERROR(I7-$I$5,"") -> 0.0084611004 | X7: 3) Maximize B36 by changing B29:B35
A8: Scenario 3 favored | B8: 0.2 | C8: 0.2 | D8: 0.6 | E8: 5 | F8: 6 | G8: 4 | H8: 10 | I8: 2.5525873 | J8: Elite Mentor Network / Smart Work-Study, Aalto-Controlled Core Infrastructure, Aalto-Certified Micro-Credentials, Pedagogical Training for Staff | K8: 4.9 | L8: 6 | M8: 5.2 | N8: =IF(SUMPRODUCT(--(O8:U8=$O$5:$U$5))=7,"No","Yes") -> No | O8: =--ISNUMBER(SEARCH(O$4,$J8)) -> 0 | P8: =--ISNUMBER(SEARCH(P$4,$J8)) -> 1 | Q8: =--ISNUMBER(SEARCH(Q$4,$J8)) -> 0 | R8: =--ISNUMBER(SEARCH(R$4,$J8)) -> 1 | S8: =--ISNUMBER(SEARCH(S$4,$J8)) -> 1 | T8: =--ISNUMBER(SEARCH(T$4,$J8)) -> 1 | U8: =--ISNUMBER(SEARCH(U$4,$J8)) -> 0 | V8: Tests stronger human-first view | W8: =IFERROR(I8-$I$5,"") -> 0.090602594 | X8: 4) Keep B29:B35 as binary
A9: Budget tightened | B9: 0.11111111 | C9: 0.61111111 | D9: 0.27777778 | E9: 4.5 | F9: 6 | G9: 4 | H9: 10 | I9: 2.4491771 | J9: AI-Enabled Student Guidance, Elite Mentor Network / Smart Work-Study, Pedagogical Training for Staff, Nordic-Baltic Tech Alliance | K9: 4.4 | L9: 6 | M9: 5 | N9: =IF(SUMPRODUCT(--(O9:U9=$O$5:$U$5))=7,"No","Yes") -> Yes | O9: =--ISNUMBER(SEARCH(O$4,$J9)) -> 1 | P9: =--ISNUMBER(SEARCH(P$4,$J9)) -> 1 | Q9: =--ISNUMBER(SEARCH(Q$4,$J9)) -> 0 | R9: =--ISNUMBER(SEARCH(R$4,$J9)) -> 0 | S9: =--ISNUMBER(SEARCH(S$4,$J9)) -> 0 | T9: =--ISNUMBER(SEARCH(T$4,$J9)) -> 1 | U9: =--ISNUMBER(SEARCH(U$4,$J9)) -> 1 | V9: Tests tighter resource envelope | W9: =IFERROR(I9-$I$5,"") -> -0.012807626 | X9: 5) Paste utility in col I
A10: Budget relaxed | B10: 0.11111111 | C10: 0.61111111 | D10: 0.27777778 | E10: 5.5 | F10: 6 | G10: 4 | H10: 10 | I10: 2.4949275 | J10: AI-Enabled Student Guidance, Elite Mentor Network / Smart Work-Study, Aalto-Controlled Core Infrastructure, Aalto-Certified Micro-Credentials | K10: 5.3 | L10: 6 | M10: 5.7 | N10: =IF(SUMPRODUCT(--(O10:U10=$O$5:$U$5))=7,"No","Yes") -> Yes | O10: =--ISNUMBER(SEARCH(O$4,$J10)) -> 1 | P10: =--ISNUMBER(SEARCH(P$4,$J10)) -> 1 | Q10: =--ISNUMBER(SEARCH(Q$4,$J10)) -> 0 | R10: =--ISNUMBER(SEARCH(R$4,$J10)) -> 1 | S10: =--ISNUMBER(SEARCH(S$4,$J10)) -> 1 | T10: =--ISNUMBER(SEARCH(T$4,$J10)) -> 0 | U10: =--ISNUMBER(SEARCH(U$4,$J10)) -> 0 | V10: Tests additional funding flexibility | W10: =IFERROR(I10-$I$5,"") -> 0.032942758 | X10: 6) Paste selected-action text in col J
A11: Capacity tightened | B11: 0.11111111 | C11: 0.61111111 | D11: 0.27777778 | E11: 5 | F11: 5 | G11: 4 | H11: 10 | I11: 2.2724274 | J11: Elite Mentor Network / Smart Work-Study, AI Governance Board / Assessment Integrity, Aalto-Controlled Core Infrastructure, Aalto-Certified Micro-Credentials | K11: 4.6 | L11: 5 | M11: 5 | N11: =IF(SUMPRODUCT(--(O11:U11=$O$5:$U$5))=7,"No","Yes") -> Yes | O11: =--ISNUMBER(SEARCH(O$4,$J11)) -> 0 | P11: =--ISNUMBER(SEARCH(P$4,$J11)) -> 1 | Q11: =--ISNUMBER(SEARCH(Q$4,$J11)) -> 1 | R11: =--ISNUMBER(SEARCH(R$4,$J11)) -> 1 | S11: =--ISNUMBER(SEARCH(S$4,$J11)) -> 1 | T11: =--ISNUMBER(SEARCH(T$4,$J11)) -> 0 | U11: =--ISNUMBER(SEARCH(U$4,$J11)) -> 0 | V11: Tests lower implementation bandwidth | W11: =IFERROR(I11-$I$5,"") -> -0.18955735 | X11: 7) Fill K:M from model outputs
A12: Max actions tightened | B12: 0.11111111 | C12: 0.61111111 | D12: 0.27777778 | E12: 5 | F12: 6 | G12: 3 | H12: 10 | I12: 1.9093012 | J12: AI-Enabled Student Guidance, Elite Mentor Network / Smart Work-Study, Pedagogical Training for Staff | K12: 3 | L12: 5 | M12: 3.5 | N12: =IF(SUMPRODUCT(--(O12:U12=$O$5:$U$5))=7,"No","Yes") -> Yes | O12: =--ISNUMBER(SEARCH(O$4,$J12)) -> 1 | P12: =--ISNUMBER(SEARCH(P$4,$J12)) -> 1 | Q12: =--ISNUMBER(SEARCH(Q$4,$J12)) -> 0 | R12: =--ISNUMBER(SEARCH(R$4,$J12)) -> 0 | S12: =--ISNUMBER(SEARCH(S$4,$J12)) -> 0 | T12: =--ISNUMBER(SEARCH(T$4,$J12)) -> 1 | U12: =--ISNUMBER(SEARCH(U$4,$J12)) -> 0 | V12: Tests a more focused portfolio | W12: =IFERROR(I12-$I$5,"") -> -0.55268348 | X12: Flags in O:U and status update automatically
A16: Interpretation | J16: Base portfolio
A17: If "Portfolio changed?" = No, the recommendation is robust to that one-way change. | J17: =J5 -> Elite Mentor Network / Smart Work-Study, Aalto-Controlled Core Infrastructure, Aalto-Certified Micro-Credentials, Pedagogical Training for Staff
A18: If it changes, the case reveals a key sensitivity that should be discussed in the report. | J18: Base expected portfolio utility | K18: =I5 -> 2.4619847
A19: Base case now updates directly from Portfolio model. In this workbook, the base portfolio is stable under probability changes, but changes under tighter budget/capacity limits and under a stricter action-count limit.
